{"version": 0.6, "generator": "Overpass API 0.7.57.1 74a55df1", "osm3s": {"timestamp_osm_base": "2022-04-10T16:00:43Z", "copyright": "The data included in this document is from www.openstreetmap.org. The data is made available under ODbL."}, "elements": [{"type": "node", "id": 84687274, "lat": 47.4319902, "lon": 19.0704928}, {"type": "node", "id": 84689061, "lat": 47.4241501, "lon": 19.0698774}, {"type": "node", "id": 84690999, "lat": 47.4304812, "lon": 19.0675308}, {"type": "node", "id": 84691002, "lat": 47.4246462, "lon": 19.0670392}, {"type": "node", "id": 84693632, "lat": 47.430286, "lon": 19.0725459}, {"type": "node", "id": 84693633, "lat": 47.4303605, "lon": 19.0703836}, {"type": "node", "id": 84693635, "lat": 47.4305951, "lon": 19.0655767}, {"type": "node", "id": 84693705, "lat": 47.4321063, "lon": 19.0677182, "tags": {"crossing:barrier": "no", "railway": "level_crossing"}}, {"type": "node", "id": 84694657, "lat": 47.4321089, "lon": 19.0676436}, {"type": "node", "id": 154480703, "lat": 47.4319195, "lon": 19.0726814}, {"type": "node", "id": 244926007, "lat": 47.4304732, "lon": 19.0677317}, {"type": "node", "id": 244926008, "lat": 47.4320866, "lon": 19.0678454}, {"type": "node", "id": 244929127, "lat": 47.4264741, "lon": 19.0782756}, {"type": "node", "id": 244929128, "lat": 47.4265579, "lon": 19.0753278}, {"type": "node", "id": 244929129, "lat": 47.4266713, "lon": 19.0722536}, {"type": "node", "id": 281868324, "lat": 47.4324895, "lon": 19.0786007}, {"type": "node", "id": 282196265, "lat": 47.4327296, "lon": 19.0727565}, {"type": "node", "id": 282197417, "lat": 47.4279901, "lon": 19.0754322}, {"type": "node", "id": 282197548, "lat": 47.4326085, "lon": 19.075812}, {"type": "node", "id": 282198529, "lat": 47.4339845, "lon": 19.072884}, {"type": "node", "id": 320651986, "lat": 47.4354405, "lon": 19.0667574, "tags": {"highway": "traffic_signals", "traffic_signals": "signal"}}, {"type": "node", "id": 320653544, "lat": 47.4307081, "lon": 19.0614344}, {"type": "node", "id": 320654003, "lat": 47.4276986, "lon": 19.0584244}, {"type": "node", "id": 322687673, "lat": 47.4276571, "lon": 19.0813}, {"type": "node", "id": 367657132, "lat": 47.4229335, "lon": 19.0719227}, {"type": "node", "id": 514817227, "lat": 47.4321495, "lon": 19.0665005}, {"type": "node", "id": 514817230, "lat": 47.4305519, "lon": 19.0663719}, {"type": "node", "id": 514832798, "lat": 47.4259509, "lon": 19.0562753}, {"type": "node", "id": 514832801, "lat": 47.4274167, "lon": 19.0575289}, {"type": "node", "id": 514832805, "lat": 47.4275312, "lon": 19.0579879}, {"type": "node", "id": 514868748, "lat": 47.4203157, "lon": 19.0731702}, {"type": "node", "id": 514869167, "lat": 47.4248669, "lon": 19.0736366}, {"type": "node", "id": 527360240, "lat": 47.430097, "lon": 19.0755989}, {"type": "node", "id": 527360241, "lat": 47.4298589, "lon": 19.081134}, {"type": "node", "id": 527360242, "lat": 47.431462, "lon": 19.0726415}, {"type": "node", "id": 527360243, "lat": 47.4313255, "lon": 19.0757031}, {"type": "node", "id": 527360244, "lat": 47.4312019, "lon": 19.0798155}, {"type": "node", "id": 527360248, "lat": 47.4290019, "lon": 19.0724445}, {"type": "node", "id": 527360249, "lat": 47.4289202, "lon": 19.0755091}, {"type": "node", "id": 527360250, "lat": 47.4287782, "lon": 19.0814682}, {"type": "node", "id": 527360251, "lat": 47.4287555, "lon": 19.0822298}, {"type": "node", "id": 527360252, "lat": 47.4281504, "lon": 19.0723564}, {"type": "node", "id": 527360258, "lat": 47.4314456, "lon": 19.0730876}, {"type": "node", "id": 527360259, "lat": 47.4281283, "lon": 19.0728307}, {"type": "node", "id": 527360260, "lat": 47.4289852, "lon": 19.0729012}, {"type": "node", "id": 527360261, "lat": 47.4302278, "lon": 19.0729845}, {"type": "node", "id": 527360262, "lat": 47.4266149, "lon": 19.0737701}, {"type": "node", "id": 527360263, "lat": 47.4280723, "lon": 19.0739024}, {"type": "node", "id": 527360264, "lat": 47.4249248, "lon": 19.0720965}, {"type": "node", "id": 527360265, "lat": 47.4248063, "lon": 19.0751568}, {"type": "node", "id": 546925885, "lat": 47.4222585, "lon": 19.0613043}, {"type": "node", "id": 546925888, "lat": 47.4268566, "lon": 19.0637274}, {"type": "node", "id": 546925890, "lat": 47.4269037, "lon": 19.0637582}, {"type": "node", "id": 546925892, "lat": 47.426941, "lon": 19.063791}, {"type": "node", "id": 546925894, "lat": 47.4269793, "lon": 19.063845}, {"type": "node", "id": 546925896, "lat": 47.4269982, "lon": 19.0639383}, {"type": "node", "id": 546925898, "lat": 47.4268156, "lon": 19.0671997, "tags": {"crossing": "marked", "highway": "crossing"}}, {"type": "node", "id": 546925901, "lat": 47.4268101, "lon": 19.0674025, "tags": {"crossing": "marked", "highway": "crossing"}}, {"type": "node", "id": 546925903, "lat": 47.4267712, "lon": 19.0701024, "tags": {"button_operated": "yes", "crossing": "traffic_signals", "crossing:island": "no", "crossing_ref": "zebra", "highway": "crossing", "tactile_paving": "yes", "traffic_signals:sound": "no", "traffic_signals:vibration": "yes"}}, {"type": "node", "id": 546925908, "lat": 47.4265229, "lon": 19.0722412}, {"type": "node", "id": 546925910, "lat": 47.426874, "lon": 19.0722677}, {"type": "node", "id": 546925948, "lat": 47.4300313, "lon": 19.0703617}, {"type": "node", "id": 546925956, "lat": 47.4219714, "lon": 19.062443}, {"type": "node", "id": 546925962, "lat": 47.4269095, "lon": 19.0665885}, {"type": "node", "id": 546925964, "lat": 47.4235229, "lon": 19.0647915}, {"type": "node", "id": 546925969, "lat": 47.4232575, "lon": 19.0661137}, {"type": "node", "id": 546925971, "lat": 47.4233511, "lon": 19.0669362}, {"type": "node", "id": 546925972, "lat": 47.4255132, "lon": 19.0658863}, {"type": "node", "id": 546925975, "lat": 47.4222975, "lon": 19.0641512}, {"type": "node", "id": 546925981, "lat": 47.4232834, "lon": 19.0658286}, {"type": "node", "id": 546926082, "lat": 47.4370265, "lon": 19.0666174}, {"type": "node", "id": 546926131, "lat": 47.4345123, "lon": 19.0680345}, {"type": "node", "id": 546926138, "lat": 47.4320229, "lon": 19.0691213}, {"type": "node", "id": 546926140, "lat": 47.4330623, "lon": 19.0692015}, {"type": "node", "id": 546926142, "lat": 47.433072, "lon": 19.0690213}, {"type": "node", "id": 546926144, "lat": 47.4330899, "lon": 19.0689751}, {"type": "node", "id": 546926145, "lat": 47.4331256, "lon": 19.0689421}, {"type": "node", "id": 546926146, "lat": 47.4331725, "lon": 19.0689322}, {"type": "node", "id": 546926147, "lat": 47.4339403, "lon": 19.0689967}, {"type": "node", "id": 546926148, "lat": 47.4339716, "lon": 19.0690165}, {"type": "node", "id": 546926149, "lat": 47.4339939, "lon": 19.0690561}, {"type": "node", "id": 546926150, "lat": 47.434005, "lon": 19.069099}, {"type": "node", "id": 546926151, "lat": 47.4340045, "lon": 19.0692915}, {"type": "node", "id": 546926152, "lat": 47.4343003, "lon": 19.0719714, "tags": {"noexit": "yes"}}, {"type": "node", "id": 546926154, "lat": 47.4319497, "lon": 19.0717589}, {"type": "node", "id": 546926163, "lat": 47.4346456, "lon": 19.072952}, {"type": "node", "id": 546926192, "lat": 47.4245539, "lon": 19.0699176}, {"type": "node", "id": 546926199, "lat": 47.42383, "lon": 19.0720121}, {"type": "node", "id": 546926222, "lat": 47.4245692, "lon": 19.0693882}, {"type": "node", "id": 546926224, "lat": 47.4251483, "lon": 19.069438}, {"type": "node", "id": 546926232, "lat": 47.4251317, "lon": 19.0699631}, {"type": "node", "id": 546926233, "lat": 47.4251334, "lon": 19.0641957}, {"type": "node", "id": 546926234, "lat": 47.4248254, "lon": 19.0655275}, {"type": "node", "id": 546926236, "lat": 47.4283751, "lon": 19.0673566}, {"type": "node", "id": 546926237, "lat": 47.4283942, "lon": 19.0666641}, {"type": "node", "id": 546926238, "lat": 47.4294475, "lon": 19.0661338}, {"type": "node", "id": 546926239, "lat": 47.4295786, "lon": 19.0661501}, {"type": "node", "id": 546926240, "lat": 47.4298345, "lon": 19.0662645}, {"type": "node", "id": 546926241, "lat": 47.4300115, "lon": 19.0663206}, {"type": "node", "id": 653971333, "lat": 47.4228915, "lon": 19.0734368}, {"type": "node", "id": 1020418813, "lat": 47.4302582, "lon": 19.0675179}, {"type": "node", "id": 1020419089, "lat": 47.4280045, "lon": 19.0658841}, {"type": "node", "id": 1020419184, "lat": 47.4345317, "lon": 19.0678544}, {"type": "node", "id": 1020419650, "lat": 47.4305829, "lon": 19.0677517, "tags": {"crossing": "marked", "highway": "crossing", "tactile_paving": "no"}}, {"type": "node", "id": 1020420024, "lat": 47.426897, "lon": 19.0672052}, {"type": "node", "id": 1020420068, "lat": 47.4305944, "lon": 19.067541, "tags": {"crossing": "marked", "highway": "crossing", "tactile_paving": "no"}}, {"type": "node", "id": 1020420490, "lat": 47.4352014, "lon": 19.0680636}, {"type": "node", "id": 1020420984, "lat": 47.4275412, "lon": 19.0656939}, {"type": "node", "id": 1020421208, "lat": 47.4304772, "lon": 19.067658, "tags": {"crossing:barrier": "no", "railway": "level_crossing"}}, {"type": "node", "id": 1020421741, "lat": 47.4269456, "lon": 19.0654176}, {"type": "node", "id": 1020422006, "lat": 47.4304777, "lon": 19.067607, "tags": {"crossing:barrier": "no", "railway": "level_crossing"}}, {"type": "node", "id": 1020423332, "lat": 47.4257132, "lon": 19.067135}, {"type": "node", "id": 1020423511, "lat": 47.431977, "lon": 19.0678383, "tags": {"crossing": "marked", "highway": "crossing", "tactile_paving": "no"}}, {"type": "node", "id": 1020423845, "lat": 47.4284162, "lon": 19.0660303}, {"type": "node", "id": 1020424125, "lat": 47.4319841, "lon": 19.0676308, "tags": {"crossing": "marked", "highway": "crossing", "tactile_paving": "no"}}, {"type": "node", "id": 1020424161, "lat": 47.4280359, "lon": 19.0672972}, {"type": "node", "id": 1020424278, "lat": 47.4321044, "lon": 19.0677696, "tags": {"crossing:barrier": "no", "railway": "level_crossing"}}, {"type": "node", "id": 1020425922, "lat": 47.4282926, "lon": 19.0660056}, {"type": "node", "id": 1039510283, "lat": 47.4283551, "lon": 19.0675472}, {"type": "node", "id": 1039510284, "lat": 47.4294027, "lon": 19.0676159}, {"type": "node", "id": 1318819100, "lat": 47.4302532, "lon": 19.0677109}, {"type": "node", "id": 1318819101, "lat": 47.4352788, "lon": 19.0680871}, {"type": "node", "id": 1319179771, "lat": 47.4302537, "lon": 19.0703765, "tags": {"button_operated": "no", "crossing": "traffic_signals", "crossing:island": "no", "highway": "crossing", "tactile_paving": "yes", "traffic_signals:sound": "no", "traffic_signals:vibration": "no"}}, {"type": "node", "id": 1319179790, "lat": 47.4303239, "lon": 19.071609}, {"type": "node", "id": 1319179793, "lat": 47.4303559, "lon": 19.0705302, "tags": {"button_operated": "no", "crossing": "traffic_signals", "highway": "crossing", "tactile_paving": "yes", "traffic_signals:sound": "no", "traffic_signals:vibration": "no"}}, {"type": "node", "id": 1319179795, "lat": 47.4303628, "lon": 19.070242, "tags": {"button_operated": "no", "crossing": "traffic_signals", "highway": "crossing", "tactile_paving": "yes", "traffic_signals:sound": "no", "traffic_signals:vibration": "no"}}, {"type": "node", "id": 1319179807, "lat": 47.4304938, "lon": 19.0703877, "tags": {"button_operated": "no", "crossing": "traffic_signals", "crossing:island": "no", "highway": "crossing", "tactile_paving": "yes", "traffic_signals:sound": "no", "traffic_signals:vibration": "no"}}, {"type": "node", "id": 1319179812, "lat": 47.4306249, "lon": 19.0716319}, {"type": "node", "id": 1319180072, "lat": 47.4313376, "lon": 19.0716864}, {"type": "node", "id": 1319180095, "lat": 47.4318751, "lon": 19.0704851, "tags": {"button_operated": "no", "crossing": "traffic_signals", "crossing:island": "no", "highway": "crossing", "tactile_paving": "yes", "traffic_signals:sound": "yes", "traffic_signals:vibration": "no"}}, {"type": "node", "id": 1319180110, "lat": 47.4319823, "lon": 19.0706467, "tags": {"button_operated": "no", "crossing": "traffic_signals", "highway": "crossing", "tactile_paving": "yes", "traffic_signals:sound": "yes", "traffic_signals:vibration": "no"}}, {"type": "node", "id": 1319180112, "lat": 47.4319825, "lon": 19.0703423, "tags": {"button_operated": "no", "crossing": "traffic_signals", "highway": "crossing", "tactile_paving": "yes", "traffic_signals:sound": "no", "traffic_signals:vibration": "no"}}, {"type": "node", "id": 1319180120, "lat": 47.4320977, "lon": 19.0704994, "tags": {"highway": "traffic_signals", "traffic_signals:direction": "backward"}}, {"type": "node", "id": 1319217100, "lat": 47.4294048, "lon": 19.0673881}, {"type": "node", "id": 1319217109, "lat": 47.4304678, "lon": 19.0678561, "tags": {"crossing": "marked", "highway": "crossing", "tactile_paving": "no"}}, {"type": "node", "id": 1319217117, "lat": 47.4304938, "lon": 19.0674164, "tags": {"crossing": "marked", "crossing:island": "no", "highway": "crossing", "tactile_paving": "no"}}, {"type": "node", "id": 1319217238, "lat": 47.4320766, "lon": 19.0679353, "tags": {"crossing": "uncontrolled", "highway": "crossing", "tactile_paving": "no"}}, {"type": "node", "id": 1319217240, "lat": 47.4321117, "lon": 19.0675647, "tags": {"highway": "crossing"}}, {"type": "node", "id": 1319217246, "lat": 47.432221, "lon": 19.0665077, "tags": {"crossing": "traffic_signals", "crossing:island": "no", "crossing_ref": "zebra", "highway": "crossing", "tactile_paving": "yes"}}, {"type": "node", "id": 1319217249, "lat": 47.4322485, "lon": 19.0678464}, {"type": "node", "id": 1319217255, "lat": 47.4322534, "lon": 19.067657}, {"type": "node", "id": 1319852150, "lat": 47.4229139, "lon": 19.0616354}, {"type": "node", "id": 1319852151, "lat": 47.4248311, "lon": 19.0583932}, {"type": "node", "id": 1319852152, "lat": 47.425464, "lon": 19.0629796}, {"type": "node", "id": 1319852153, "lat": 47.4257057, "lon": 19.0673294}, {"type": "node", "id": 1319852156, "lat": 47.4280331, "lon": 19.0675154}, {"type": "node", "id": 1319852158, "lat": 47.4283216, "lon": 19.0688443}, {"type": "node", "id": 1319852165, "lat": 47.4353123, "lon": 19.0681193, "tags": {"crossing": "marked", "crossing_ref": "zebra", "highway": "crossing", "tactile_paving": "no"}}, {"type": "node", "id": 1412912008, "lat": 47.4246, "lon": 19.0659542}, {"type": "node", "id": 1413107923, "lat": 47.4240641, "lon": 19.0611612}, {"type": "node", "id": 1413107957, "lat": 47.4302162, "lon": 19.0610249}, {"type": "node", "id": 1413107970, "lat": 47.4251246, "lon": 19.061769}, {"type": "node", "id": 1413107975, "lat": 47.4233746, "lon": 19.0607864}, {"type": "node", "id": 1413107986, "lat": 47.4296571, "lon": 19.0604959}, {"type": "node", "id": 1413108012, "lat": 47.4286245, "lon": 19.0594227}, {"type": "node", "id": 1413108033, "lat": 47.429038, "lon": 19.0598524}, {"type": "node", "id": 1425843611, "lat": 47.4321319, "lon": 19.0691344, "tags": {"crossing": "unmarked", "crossing:island": "no", "highway": "crossing", "kerb": "lowered", "tactile_paving": "no"}}, {"type": "node", "id": 1704207787, "lat": 47.4326248, "lon": 19.075355}, {"type": "node", "id": 1704207795, "lat": 47.4325952, "lon": 19.0762153}, {"type": "node", "id": 1704207815, "lat": 47.4325523, "lon": 19.0770239}, {"type": "node", "id": 1704207824, "lat": 47.4325667, "lon": 19.0768498}, {"type": "node", "id": 1704207840, "lat": 47.4326061, "lon": 19.0760223}, {"type": "node", "id": 1704207847, "lat": 47.4325752, "lon": 19.0766651}, {"type": "node", "id": 1704215394, "lat": 47.432517, "lon": 19.0779315}, {"type": "node", "id": 1704215397, "lat": 47.4325258, "lon": 19.0777197}, {"type": "node", "id": 1704215400, "lat": 47.4325314, "lon": 19.0774836}, {"type": "node", "id": 1876545352, "lat": 47.4305843, "lon": 19.0658458, "tags": {"highway": "traffic_signals", "traffic_signals": "signal"}}, {"type": "node", "id": 1876545353, "lat": 47.4269627, "lon": 19.0649312}, {"type": "node", "id": 1876545354, "lat": 47.4321674, "lon": 19.0659985, "tags": {"highway": "traffic_signals", "traffic_signals": "signal"}}, {"type": "node", "id": 1876545355, "lat": 47.4353345, "lon": 19.0662451, "tags": {"addr:street": "Teller Ede \u00fat", "button_operated": "yes", "crossing": "traffic_signals", "crossing:island": "yes", "crossing_ref": "zebra", "description": "vsb plus", "highway": "traffic_signals", "supervised": "no", "tactile_paving": "yes", "traffic_signals:sound": "yes", "traffic_signals:vibration": "no", "website": "https://www.vgyke.com/hir/eligazodva-a-varosban/"}}, {"type": "node", "id": 1876545356, "lat": 47.4287794, "lon": 19.0656247}, {"type": "node", "id": 1876545357, "lat": 47.4275147, "lon": 19.0652084}, {"type": "node", "id": 1876545358, "lat": 47.422009, "lon": 19.0622861}, {"type": "node", "id": 1876545360, "lat": 47.4263882, "lon": 19.0646258}, {"type": "node", "id": 1876545361, "lat": 47.4354634, "lon": 19.0662588, "tags": {"highway": "traffic_signals", "traffic_signals": "signal"}}, {"type": "node", "id": 1876545362, "lat": 47.4254968, "lon": 19.0640953}, {"type": "node", "id": 1877488587, "lat": 47.4238791, "lon": 19.0632617}, {"type": "node", "id": 1877488588, "lat": 47.4235889, "lon": 19.064568}, {"type": "node", "id": 1877785773, "lat": 47.4306019, "lon": 19.0651419}, {"type": "node", "id": 1877819070, "lat": 47.4306727, "lon": 19.0623197}, {"type": "node", "id": 1877833306, "lat": 47.4222081, "lon": 19.0626714}, {"type": "node", "id": 1877833308, "lat": 47.4294024, "lon": 19.0674446}, {"type": "node", "id": 1877833313, "lat": 47.4244731, "lon": 19.0635629}, {"type": "node", "id": 1877833317, "lat": 47.4241555, "lon": 19.0636657}, {"type": "node", "id": 1877833319, "lat": 47.4235679, "lon": 19.0633388}, {"type": "node", "id": 1877833327, "lat": 47.4264241, "lon": 19.0648775}, {"type": "node", "id": 1945984555, "lat": 47.4203556, "lon": 19.0732308}, {"type": "node", "id": 1945984557, "lat": 47.4203855, "lon": 19.0732588}, {"type": "node", "id": 2026329302, "lat": 47.4283086, "lon": 19.0692793}, {"type": "node", "id": 2026329303, "lat": 47.4283636, "lon": 19.0702297, "tags": {"crossing": "marked", "crossing:island": "yes", "highway": "crossing", "tactile_paving": "yes"}}, {"type": "node", "id": 2026329307, "lat": 47.4295981, "lon": 19.0703297}, {"type": "node", "id": 2026329308, "lat": 47.4296155, "lon": 19.069571}, {"type": "node", "id": 2026329309, "lat": 47.4296351, "lon": 19.0689192}, {"type": "node", "id": 2026329310, "lat": 47.4304197, "lon": 19.068974}, {"type": "node", "id": 2026341868, "lat": 47.4268987, "lon": 19.0671661}, {"type": "node", "id": 2026341876, "lat": 47.4283766, "lon": 19.0673022}, {"type": "node", "id": 2026341879, "lat": 47.4283822, "lon": 19.0670803}, {"type": "node", "id": 2026341881, "lat": 47.4294119, "lon": 19.0671662}, {"type": "node", "id": 2026341883, "lat": 47.4294146, "lon": 19.067109}, {"type": "node", "id": 2038247255, "lat": 47.4268557, "lon": 19.0701092}, {"type": "node", "id": 2038247256, "lat": 47.4282932, "lon": 19.070224}, {"type": "node", "id": 2041821193, "lat": 47.4303504, "lon": 19.0689691}, {"type": "node", "id": 2041929910, "lat": 47.4293931, "lon": 19.0661296, "tags": {"barrier": "lift_gate"}}, {"type": "node", "id": 2041929911, "lat": 47.4284933, "lon": 19.0660385, "tags": {"barrier": "lift_gate"}}, {"type": "node", "id": 2046242001, "lat": 47.4269449, "lon": 19.0691826, "tags": {"barrier": "bollard"}}, {"type": "node", "id": 2046242006, "lat": 47.4273102, "lon": 19.0692084}, {"type": "node", "id": 2052435200, "lat": 47.4272526, "lon": 19.0692043}, {"type": "node", "id": 2052435202, "lat": 47.4275033, "lon": 19.0692221}, {"type": "node", "id": 2052435205, "lat": 47.4276608, "lon": 19.0692333}, {"type": "node", "id": 2052435207, "lat": 47.4279307, "lon": 19.0692496}, {"type": "node", "id": 2052435209, "lat": 47.4281394, "lon": 19.0692644}, {"type": "node", "id": 2056021561, "lat": 47.4294024, "lon": 19.0689055}, {"type": "node", "id": 2060235382, "lat": 47.4273316, "lon": 19.0687406}, {"type": "node", "id": 2060239364, "lat": 47.4295985, "lon": 19.0701871}, {"type": "node", "id": 2077721406, "lat": 47.424608, "lon": 19.0693899}, {"type": "node", "id": 2113685774, "lat": 47.4304527, "lon": 19.0677305, "tags": {"direction": "forward", "highway": "stop"}}, {"type": "node", "id": 2113685778, "lat": 47.4321134, "lon": 19.0665021}, {"type": "node", "id": 2113696874, "lat": 47.4302241, "lon": 19.0703745, "tags": {"highway": "traffic_signals", "traffic_signals:direction": "forward"}}, {"type": "node", "id": 2113696882, "lat": 47.4303539, "lon": 19.0705746, "tags": {"highway": "traffic_signals"}}, {"type": "node", "id": 2113696903, "lat": 47.4318439, "lon": 19.0704841, "tags": {"highway": "traffic_signals", "traffic_signals:direction": "backward"}}, {"type": "node", "id": 2113696917, "lat": 47.431984, "lon": 19.0702955, "tags": {"highway": "traffic_signals"}}, {"type": "node", "id": 2113794533, "lat": 47.4245367, "lon": 19.0672123}, {"type": "node", "id": 2113794589, "lat": 47.424746, "lon": 19.067226}, {"type": "node", "id": 2119558410, "lat": 47.4248611, "lon": 19.0694124}, {"type": "node", "id": 2121174315, "lat": 47.4343337, "lon": 19.069323}, {"type": "node", "id": 2121174318, "lat": 47.4343479, "lon": 19.0689558, "tags": {"noexit": "yes"}}, {"type": "node", "id": 2121206482, "lat": 47.4345811, "lon": 19.0680354}, {"type": "node", "id": 2124795081, "lat": 47.4295996, "lon": 19.0701685, "tags": {"highway": "give_way"}}, {"type": "node", "id": 2129792938, "lat": 47.4290798, "lon": 19.0702869}, {"type": "node", "id": 2129797000, "lat": 47.4301967, "lon": 19.0725384, "tags": {"crossing": "traffic_signals", "crossing:island": "no", "highway": "crossing", "tactile_paving": "no"}}, {"type": "node", "id": 2129797006, "lat": 47.430296, "lon": 19.0724668, "tags": {"button_operated": "no", "crossing": "traffic_signals", "crossing:island": "no", "highway": "crossing", "tactile_paving": "no", "traffic_signals:sound": "no", "traffic_signals:vibration": "no"}}, {"type": "node", "id": 2129804865, "lat": 47.4269596, "lon": 19.0650807, "tags": {"highway": "traffic_signals"}}, {"type": "node", "id": 2132914713, "lat": 47.4291873, "lon": 19.0688904}, {"type": "node", "id": 2132914720, "lat": 47.4296236, "lon": 19.0692767}, {"type": "node", "id": 2139223129, "lat": 47.4294061, "lon": 19.0673481, "tags": {"direction": "forward", "highway": "give_way"}}, {"type": "node", "id": 2139223130, "lat": 47.4294441, "lon": 19.0662201, "tags": {"direction": "backward", "highway": "give_way"}}, {"type": "node", "id": 2139223133, "lat": 47.4319625, "lon": 19.0678359, "tags": {"direction": "forward", "highway": "give_way"}}, {"type": "node", "id": 2144602474, "lat": 47.4319206, "lon": 19.0725559, "tags": {"highway": "traffic_signals", "traffic_signals:direction": "forward"}}, {"type": "node", "id": 2145731888, "lat": 47.4304206, "lon": 19.0663556, "tags": {"highway": "traffic_signals", "traffic_signals": "signal", "traffic_signals:direction": "forward"}}, {"type": "node", "id": 2145731902, "lat": 47.4305398, "lon": 19.066552, "tags": {"highway": "traffic_signals", "traffic_signals:direction": "forward"}}, {"type": "node", "id": 2145731906, "lat": 47.4305432, "lon": 19.066499, "tags": {"crossing": "traffic_signals", "crossing:island": "no", "crossing_ref": "zebra", "highway": "crossing", "supervised": "no", "tactile_paving": "yes"}}, {"type": "node", "id": 2145731910, "lat": 47.4305758, "lon": 19.0659903, "tags": {"highway": "traffic_signals"}}, {"type": "node", "id": 2145731914, "lat": 47.4306382, "lon": 19.0663772, "tags": {"crossing": "traffic_signals", "crossing:island": "no", "crossing_ref": "zebra", "highway": "crossing", "tactile_paving": "yes"}}, {"type": "node", "id": 2149571480, "lat": 47.4252358, "lon": 19.069974}, {"type": "node", "id": 2149954018, "lat": 47.4321448, "lon": 19.0666334, "tags": {"highway": "traffic_signals", "traffic_signals:direction": "backward"}}, {"type": "node", "id": 2149954114, "lat": 47.4321622, "lon": 19.0661428, "tags": {"highway": "traffic_signals"}}, {"type": "node", "id": 2149955676, "lat": 47.4270711, "lon": 19.0691914}, {"type": "node", "id": 2150875423, "lat": 47.4246776, "lon": 19.0696787}, {"type": "node", "id": 2150875424, "lat": 47.4246853, "lon": 19.0697285}, {"type": "node", "id": 2150875425, "lat": 47.4246869, "lon": 19.0693969}, {"type": "node", "id": 2150875426, "lat": 47.4247128, "lon": 19.0697579}, {"type": "node", "id": 2150875427, "lat": 47.4251368, "lon": 19.06977}, {"type": "node", "id": 2150893322, "lat": 47.4318833, "lon": 19.0717503}, {"type": "node", "id": 2150893324, "lat": 47.4319201, "lon": 19.0725938, "tags": {"button_operated": "no", "crossing": "traffic_signals", "highway": "crossing", "tactile_paving": "no", "traffic_signals:sound": "no", "traffic_signals:vibration": "no"}}, {"type": "node", "id": 2153340901, "lat": 47.4238811, "lon": 19.0698184, "tags": {"crossing": "marked", "crossing:island": "yes", "highway": "crossing", "tactile_paving": "yes"}}, {"type": "node", "id": 2160949504, "lat": 47.435343, "lon": 19.0678075, "tags": {"crossing": "unmarked", "crossing_ref": "zebra", "highway": "crossing", "tactile_paving": "yes"}}, {"type": "node", "id": 2160949531, "lat": 47.4353678, "lon": 19.0667545, "tags": {"crossing": "traffic_signals", "crossing:island": "no", "crossing_ref": "zebra", "highway": "crossing", "tactile_paving": "yes"}}, {"type": "node", "id": 2163574207, "lat": 47.4260691, "lon": 19.067354}, {"type": "node", "id": 2165192534, "lat": 47.4284331, "lon": 19.0702352}, {"type": "node", "id": 2165192538, "lat": 47.4290132, "lon": 19.0702816}, {"type": "node", "id": 2169116304, "lat": 47.423981, "lon": 19.0698403}, {"type": "node", "id": 2169116309, "lat": 47.4245149, "lon": 19.0699137}, {"type": "node", "id": 2169116313, "lat": 47.4246003, "lon": 19.0699215}, {"type": "node", "id": 2169116325, "lat": 47.4253485, "lon": 19.0699834}, {"type": "node", "id": 2169116328, "lat": 47.4265582, "lon": 19.0700846}, {"type": "node", "id": 2171619784, "lat": 47.4284052, "lon": 19.070233}, {"type": "node", "id": 2195737929, "lat": 47.4335134, "lon": 19.0706348, "tags": {"crossing": "uncontrolled", "crossing:island": "yes", "crossing_ref": "zebra", "highway": "crossing", "supervised": "no"}}, {"type": "node", "id": 2207117166, "lat": 47.426177, "lon": 19.0722117}, {"type": "node", "id": 2207117179, "lat": 47.4262362, "lon": 19.0722169}, {"type": "node", "id": 2217268375, "lat": 47.4329015, "lon": 19.0727737, "tags": {"crossing": "uncontrolled", "crossing:island": "yes", "highway": "crossing", "tactile_paving": "no"}}, {"type": "node", "id": 2217275302, "lat": 47.434032, "lon": 19.0728908}, {"type": "node", "id": 2235248070, "lat": 47.434243, "lon": 19.0729113, "tags": {"crossing": "uncontrolled", "crossing:island": "yes", "highway": "crossing", "tactile_paving": "no"}}, {"type": "node", "id": 2235270158, "lat": 47.4302615, "lon": 19.0726448, "tags": {"crossing": "marked", "crossing:island": "no", "highway": "crossing", "tactile_paving": "no"}}, {"type": "node", "id": 2235270162, "lat": 47.4303686, "lon": 19.0725512, "tags": {"highway": "traffic_signals"}}, {"type": "node", "id": 2235270170, "lat": 47.4314579, "lon": 19.0727911, "tags": {"direction": "backward", "highway": "give_way"}}, {"type": "node", "id": 2235270175, "lat": 47.4314587, "lon": 19.0727473}, {"type": "node", "id": 2235270179, "lat": 47.4319875, "lon": 19.0726868, "tags": {"highway": "traffic_signals", "traffic_signals:direction": "forward"}}, {"type": "node", "id": 2235270185, "lat": 47.4327262, "lon": 19.0728467}, {"type": "node", "id": 2235427914, "lat": 47.4266174, "lon": 19.0722507, "tags": {"crossing": "uncontrolled", "crossing:island": "yes", "highway": "crossing", "tactile_paving": "no"}}, {"type": "node", "id": 2235427917, "lat": 47.4266676, "lon": 19.072348, "tags": {"crossing": "uncontrolled", "crossing:island": "no", "highway": "crossing", "tactile_paving": "no"}}, {"type": "node", "id": 2235427919, "lat": 47.4268081, "lon": 19.0722655, "tags": {"crossing": "uncontrolled", "crossing:island": "no", "highway": "crossing", "tactile_paving": "no"}}, {"type": "node", "id": 2235432675, "lat": 47.4281432, "lon": 19.0724739}, {"type": "node", "id": 2235432678, "lat": 47.4281795, "lon": 19.0723617, "tags": {"crossing": "uncontrolled", "crossing:island": "no", "highway": "crossing", "tactile_paving": "no"}}, {"type": "node", "id": 2239750881, "lat": 47.4318341, "lon": 19.072674, "tags": {"button_operated": "no", "crossing": "traffic_signals", "crossing:island": "no", "highway": "crossing", "tactile_paving": "no", "traffic_signals:sound": "no", "traffic_signals:vibration": "no"}}, {"type": "node", "id": 2239807000, "lat": 47.4303971, "lon": 19.071616}, {"type": "node", "id": 2244819769, "lat": 47.4305647, "lon": 19.0661614}, {"type": "node", "id": 2244819882, "lat": 47.4321568, "lon": 19.0662967}, {"type": "node", "id": 2259953795, "lat": 47.4344305, "lon": 19.0707072}, {"type": "node", "id": 2267377547, "lat": 47.4230202, "lon": 19.0719315, "tags": {"button_operated": "no", "crossing": "traffic_signals", "crossing:island": "no", "highway": "crossing", "tactile_paving": "no", "traffic_signals:sound": "yes", "traffic_signals:vibration": "no"}}, {"type": "node", "id": 2277543808, "lat": 47.4289997, "lon": 19.0725054, "tags": {"highway": "give_way"}}, {"type": "node", "id": 2278318294, "lat": 47.4303702, "lon": 19.0700778}, {"type": "node", "id": 2278318296, "lat": 47.4304618, "lon": 19.0679952}, {"type": "node", "id": 2281111500, "lat": 47.4305075, "lon": 19.0675332, "tags": {"highway": "give_way"}}, {"type": "node", "id": 2281481703, "lat": 47.4217039, "lon": 19.0638361}, {"type": "node", "id": 2281481712, "lat": 47.4220944, "lon": 19.0624835, "tags": {"button_operated": "yes", "crossing": "traffic_signals", "highway": "crossing", "tactile_paving": "yes", "traffic_signals:sound": "yes", "traffic_signals:vibration": "yes"}}, {"type": "node", "id": 2281481715, "lat": 47.4221542, "lon": 19.0625045}, {"type": "node", "id": 2281481717, "lat": 47.4223069, "lon": 19.0613034}, {"type": "node", "id": 2281481718, "lat": 47.4226141, "lon": 19.0627182}, {"type": "node", "id": 2281481719, "lat": 47.4229817, "lon": 19.0614473}, {"type": "node", "id": 2281481727, "lat": 47.4232584, "lon": 19.0660412}, {"type": "node", "id": 2281481730, "lat": 47.4236769, "lon": 19.0632967}, {"type": "node", "id": 2281481732, "lat": 47.4236333, "lon": 19.0631264}, {"type": "node", "id": 2281481733, "lat": 47.4238712, "lon": 19.0635232, "tags": {"addr:street": "Bet\u0171 utca", "button_operated": "yes", "crossing": "traffic_signals", "crossing:island": "no", "crossing_ref": "zebra", "description": "vsb plus", "highway": "traffic_signals", "supervised": "no", "tactile_paving": "yes", "traffic_signals:sound": "yes", "traffic_signals:vibration": "no", "website": "https://www.vgyke.com/hir/eligazodva-a-varosban/"}}, {"type": "node", "id": 2281481734, "lat": 47.4238996, "lon": 19.0634252}, {"type": "node", "id": 2281481736, "lat": 47.4241148, "lon": 19.063538}, {"type": "node", "id": 2281481740, "lat": 47.4254683, "lon": 19.064198}, {"type": "node", "id": 2281481742, "lat": 47.4265615, "lon": 19.0648448}, {"type": "node", "id": 2281481745, "lat": 47.4269517, "lon": 19.0652441, "tags": {"addr:street": "Kar\u00e1csony S\u00e1ndor utca", "crossing": "traffic_signals", "crossing_ref": "zebra", "highway": "crossing", "supervised": "no", "tactile_paving": "yes", "traffic_signals:sound": "yes", "traffic_signals:vibration": "no", "website": "https://www.vgyke.com/hir/eligazodva-a-varosban/"}}, {"type": "node", "id": 2281481750, "lat": 47.4276025, "lon": 19.0653702}, {"type": "node", "id": 2281481751, "lat": 47.4278442, "lon": 19.0653422}, {"type": "node", "id": 2281481752, "lat": 47.4281238, "lon": 19.0655897}, {"type": "node", "id": 2281481753, "lat": 47.4281607, "lon": 19.0654639}, {"type": "node", "id": 2281481754, "lat": 47.4287114, "lon": 19.0657438}, {"type": "node", "id": 2281481755, "lat": 47.4291016, "lon": 19.0658162}, {"type": "node", "id": 2281481756, "lat": 47.4300257, "lon": 19.0658956}, {"type": "node", "id": 2281481761, "lat": 47.4308626, "lon": 19.066042}, {"type": "node", "id": 2281481763, "lat": 47.4310698, "lon": 19.0660614}, {"type": "node", "id": 2281481764, "lat": 47.4313552, "lon": 19.06607}, {"type": "node", "id": 2281481765, "lat": 47.4319051, "lon": 19.0661241}, {"type": "node", "id": 2281481772, "lat": 47.4325151, "lon": 19.0661571}, {"type": "node", "id": 2281481773, "lat": 47.4328642, "lon": 19.0661734}, {"type": "node", "id": 2281481774, "lat": 47.433864, "lon": 19.0662692}, {"type": "node", "id": 2281481775, "lat": 47.4338719, "lon": 19.0661127}, {"type": "node", "id": 2281481776, "lat": 47.4348338, "lon": 19.0662061}, {"type": "node", "id": 2281481781, "lat": 47.4352555, "lon": 19.0663906}, {"type": "node", "id": 2281481786, "lat": 47.4354592, "lon": 19.0664163, "tags": {"highway": "traffic_signals", "traffic_signals": "signal"}}, {"type": "node", "id": 2281983974, "lat": 47.4230484, "lon": 19.0719359, "tags": {"highway": "traffic_signals"}}, {"type": "node", "id": 2281983975, "lat": 47.4231594, "lon": 19.0719467}, {"type": "node", "id": 2281983977, "lat": 47.4236474, "lon": 19.0719943}, {"type": "node", "id": 2286686288, "lat": 47.4298634, "lon": 19.0810232, "tags": {"direction": "backward", "highway": "give_way"}}, {"type": "node", "id": 2286708328, "lat": 47.4247775, "lon": 19.0760225}, {"type": "node", "id": 2286708336, "lat": 47.4253066, "lon": 19.0752056}, {"type": "node", "id": 2286708338, "lat": 47.4256888, "lon": 19.075243}, {"type": "node", "id": 2286708348, "lat": 47.4259746, "lon": 19.0752709}, {"type": "node", "id": 2286708352, "lat": 47.4265061, "lon": 19.0771487}, {"type": "node", "id": 2286708353, "lat": 47.4265176, "lon": 19.0767467}, {"type": "node", "id": 2286708354, "lat": 47.4265341, "lon": 19.0761636}, {"type": "node", "id": 2286718395, "lat": 47.4248168, "lon": 19.0720882, "tags": {"crossing": "uncontrolled", "highway": "crossing", "tactile_paving": "no"}}, {"type": "node", "id": 2286718407, "lat": 47.4248591, "lon": 19.075162}, {"type": "node", "id": 2286718413, "lat": 47.4249209, "lon": 19.0722013, "tags": {"crossing": "uncontrolled", "crossing:island": "no", "highway": "crossing", "tactile_paving": "no"}}, {"type": "node", "id": 2286718429, "lat": 47.4250048, "lon": 19.0721039, "tags": {"crossing": "uncontrolled", "highway": "crossing", "tactile_paving": "no"}}, {"type": "node", "id": 2303381774, "lat": 47.4298477, "lon": 19.068934}, {"type": "node", "id": 2303381776, "lat": 47.4302876, "lon": 19.0689647}, {"type": "node", "id": 2319944142, "lat": 47.4257442, "lon": 19.0721719}, {"type": "node", "id": 2321776718, "lat": 47.4249839, "lon": 19.0694233}, {"type": "node", "id": 2321776720, "lat": 47.4246622, "lon": 19.0693947}, {"type": "node", "id": 2321776724, "lat": 47.4247222, "lon": 19.0694}, {"type": "node", "id": 2324415266, "lat": 47.4246994, "lon": 19.0600314}, {"type": "node", "id": 2324415267, "lat": 47.4247437, "lon": 19.0600241}, {"type": "node", "id": 2324415268, "lat": 47.4249914, "lon": 19.0580505}, {"type": "node", "id": 2324415269, "lat": 47.4256111, "lon": 19.0611189}, {"type": "node", "id": 2324415270, "lat": 47.4257226, "lon": 19.0567474}, {"type": "node", "id": 2324415272, "lat": 47.4267695, "lon": 19.0570024}, {"type": "node", "id": 2324415275, "lat": 47.4275645, "lon": 19.0576786}, {"type": "node", "id": 2324415278, "lat": 47.4288866, "lon": 19.0596951}, {"type": "node", "id": 2324415283, "lat": 47.4306317, "lon": 19.0639901}, {"type": "node", "id": 2325474715, "lat": 47.4330887, "lon": 19.0705944}, {"type": "node", "id": 2520714034, "lat": 47.4248205, "lon": 19.0736319}, {"type": "node", "id": 2526611642, "lat": 47.4312992, "lon": 19.0756996}, {"type": "node", "id": 2576613482, "lat": 47.4228296, "lon": 19.0734313}, {"type": "node", "id": 2576631908, "lat": 47.4300523, "lon": 19.0755903}, {"type": "node", "id": 2576631909, "lat": 47.4300861, "lon": 19.0756611}, {"type": "node", "id": 2576631910, "lat": 47.4301052, "lon": 19.075512}, {"type": "node", "id": 2576631911, "lat": 47.4301398, "lon": 19.0755986}, {"type": "node", "id": 2576631912, "lat": 47.4325689, "lon": 19.0758103}, {"type": "node", "id": 2576852984, "lat": 47.430657, "lon": 19.0630388}, {"type": "node", "id": 2582084283, "lat": 47.429149, "lon": 19.0656901}, {"type": "node", "id": 2582084284, "lat": 47.4300431, "lon": 19.0657695}, {"type": "node", "id": 2582084286, "lat": 47.4231416, "lon": 19.0670872}, {"type": "node", "id": 2582084289, "lat": 47.4231945, "lon": 19.0670919, "tags": {"crossing": "traffic_signals", "highway": "crossing"}}, {"type": "node", "id": 2954141053, "lat": 47.4311959, "lon": 19.0664233}, {"type": "node", "id": 2967537737, "lat": 47.4256519, "lon": 19.0752394}, {"type": "node", "id": 2967566762, "lat": 47.4256867, "lon": 19.0721666}, {"type": "node", "id": 2982089896, "lat": 47.4327483, "lon": 19.0678879}, {"type": "node", "id": 3038589649, "lat": 47.4248175, "lon": 19.074876}, {"type": "node", "id": 3038589651, "lat": 47.4248745, "lon": 19.0734358}, {"type": "node", "id": 3038589653, "lat": 47.4255569, "lon": 19.0752301}, {"type": "node", "id": 3038589658, "lat": 47.4320511, "lon": 19.0683375}, {"type": "node", "id": 3038589660, "lat": 47.4324875, "lon": 19.06916}, {"type": "node", "id": 3038589662, "lat": 47.432717, "lon": 19.0691766}, {"type": "node", "id": 3038589664, "lat": 47.4327707, "lon": 19.0727606}, {"type": "node", "id": 3038589667, "lat": 47.4328283, "lon": 19.0678945}, {"type": "node", "id": 3038589669, "lat": 47.4331217, "lon": 19.0679189}, {"type": "node", "id": 3066608649, "lat": 47.4278223, "lon": 19.0783891}, {"type": "node", "id": 3090564035, "lat": 47.4329726, "lon": 19.0705833}, {"type": "node", "id": 3371431011, "lat": 47.4321224, "lon": 19.0672634}, {"type": "node", "id": 3371431012, "lat": 47.4321412, "lon": 19.0667356}, {"type": "node", "id": 3375747175, "lat": 47.4303329, "lon": 19.0713105}, {"type": "node", "id": 3385709535, "lat": 47.4311038, "lon": 19.0677845}, {"type": "node", "id": 3545111610, "lat": 47.4305347, "lon": 19.0666471}, {"type": "node", "id": 3545111611, "lat": 47.4305065, "lon": 19.0671773}, {"type": "node", "id": 3569374498, "lat": 47.4296769, "lon": 19.0703351}, {"type": "node", "id": 3876392077, "lat": 47.4312122, "lon": 19.0704387}, {"type": "node", "id": 3876392078, "lat": 47.4312654, "lon": 19.0704424}, {"type": "node", "id": 4157766784, "lat": 47.4252569, "lon": 19.0620442}, {"type": "node", "id": 4690567169, "lat": 47.4234709, "lon": 19.0594449}, {"type": "node", "id": 4690567170, "lat": 47.4238826, "lon": 19.0599517}, {"type": "node", "id": 4690584499, "lat": 47.425388, "lon": 19.0573437}, {"type": "node", "id": 4690692197, "lat": 47.4306015, "lon": 19.0651646}, {"type": "node", "id": 4886079016, "lat": 47.422124, "lon": 19.0623456, "tags": {"button_operated": "yes", "crossing": "traffic_signals", "highway": "crossing", "tactile_paving": "yes", "traffic_signals:sound": "yes", "traffic_signals:vibration": "yes"}}, {"type": "node", "id": 5139243118, "lat": 47.4353019, "lon": 19.0678557}, {"type": "node", "id": 6003108882, "lat": 47.4247298, "lon": 19.0654735}, {"type": "node", "id": 6003111908, "lat": 47.4249863, "lon": 19.0648264}, {"type": "node", "id": 6003113895, "lat": 47.4253878, "lon": 19.0660199}, {"type": "node", "id": 6003113896, "lat": 47.4254421, "lon": 19.0660151}, {"type": "node", "id": 6003113897, "lat": 47.4254788, "lon": 19.0659863}, {"type": "node", "id": 6003113898, "lat": 47.4254984, "lon": 19.0659505}, {"type": "node", "id": 6152675750, "lat": 47.4235013, "lon": 19.064885, "tags": {"crossing": "traffic_signals", "crossing:island": "no", "crossing_ref": "zebra", "highway": "crossing", "tactile_paving": "yes"}}, {"type": "node", "id": 6152675751, "lat": 47.4234918, "lon": 19.0649263, "tags": {"highway": "traffic_signals", "traffic_signals": "pedestrian_crossing", "traffic_signals:direction": "forward"}}, {"type": "node", "id": 6190400270, "lat": 47.4269277, "lon": 19.0659987}, {"type": "node", "id": 6190442829, "lat": 47.4221701, "lon": 19.0625956}, {"type": "node", "id": 6190442834, "lat": 47.4236698, "lon": 19.064306}, {"type": "node", "id": 6190442836, "lat": 47.4238986, "lon": 19.0633453}, {"type": "node", "id": 6190578042, "lat": 47.4238091, "lon": 19.0669726}, {"type": "node", "id": 6190798619, "lat": 47.4345066, "lon": 19.0707124}, {"type": "node", "id": 6190798620, "lat": 47.432756, "lon": 19.0705625}, {"type": "node", "id": 6190798621, "lat": 47.4320097, "lon": 19.0695969}, {"type": "node", "id": 6190798622, "lat": 47.4315574, "lon": 19.0704631}, {"type": "node", "id": 6900286794, "lat": 47.4269074, "lon": 19.0666986}, {"type": "node", "id": 7899955084, "lat": 47.431981, "lon": 19.0707069}, {"type": "node", "id": 7945906613, "lat": 47.4334599, "lon": 19.0706297}, {"type": "node", "id": 7945906614, "lat": 47.4249006, "lon": 19.0699443}, {"type": "node", "id": 8091097977, "lat": 47.4247803, "lon": 19.0584767}, {"type": "node", "id": 8111199653, "lat": 47.4239088, "lon": 19.0720182, "tags": {"crossing": "uncontrolled", "crossing:island": "yes", "highway": "crossing", "tactile_paving": "yes"}}, {"type": "node", "id": 8517696597, "lat": 47.4353302, "lon": 19.0664, "tags": {"addr:street": "Teller Ede \u00fat", "button_operated": "yes", "crossing": "traffic_signals", "crossing:island": "yes", "crossing_ref": "zebra", "description": "vsb plus", "highway": "traffic_signals", "supervised": "no", "tactile_paving": "yes", "traffic_signals:sound": "yes", "traffic_signals:vibration": "no", "website": "https://www.vgyke.com/hir/eligazodva-a-varosban/"}}, {"type": "node", "id": 8517696598, "lat": 47.4355353, "lon": 19.066749, "tags": {"crossing": "traffic_signals", "crossing:island": "no", "crossing_ref": "zebra", "highway": "crossing", "tactile_paving": "yes"}}, {"type": "node", "id": 8517713340, "lat": 47.4323064, "lon": 19.0660098, "tags": {"addr:street": "Teller Ede \u00fat", "button_operated": "yes", "crossing": "traffic_signals", "crossing:island": "yes", "crossing_ref": "zebra", "description": "vsb plus", "highway": "traffic_signals", "supervised": "no", "tactile_paving": "yes", "traffic_signals:sound": "yes", "traffic_signals:vibration": "no", "website": "https://www.vgyke.com/hir/eligazodva-a-varosban/"}}, {"type": "node", "id": 8517713341, "lat": 47.4323024, "lon": 19.0661494, "tags": {"addr:street": "Teller Ede \u00fat", "button_operated": "yes", "crossing": "traffic_signals", "crossing:island": "yes", "crossing_ref": "zebra", "description": "vsb plus", "highway": "traffic_signals", "supervised": "no", "tactile_paving": "yes", "traffic_signals:sound": "yes", "traffic_signals:vibration": "no", "website": "https://www.vgyke.com/hir/eligazodva-a-varosban/"}}, {"type": "node", "id": 8517713342, "lat": 47.4320752, "lon": 19.0659907, "tags": {"addr:street": "Teller Ede \u00fat", "button_operated": "yes", "crossing": "traffic_signals", "crossing:island": "yes", "crossing_ref": "zebra", "description": "vsb plus", "highway": "traffic_signals", "supervised": "no", "tactile_paving": "yes", "traffic_signals:sound": "yes", "traffic_signals:vibration": "no", "website": "https://www.vgyke.com/hir/eligazodva-a-varosban/"}}, {"type": "node", "id": 8517713343, "lat": 47.4320671, "lon": 19.0661362, "tags": {"addr:street": "Teller Ede \u00fat", "button_operated": "yes", "crossing": "traffic_signals", "crossing:island": "yes", "crossing_ref": "zebra", "description": "vsb plus", "highway": "traffic_signals", "supervised": "no", "tactile_paving": "yes", "traffic_signals:sound": "yes", "traffic_signals:vibration": "no", "website": "https://www.vgyke.com/hir/eligazodva-a-varosban/"}}, {"type": "node", "id": 8517713344, "lat": 47.432154, "lon": 19.0663743, "tags": {"crossing": "traffic_signals", "crossing:island": "no", "crossing_ref": "zebra", "highway": "crossing", "tactile_paving": "yes"}}, {"type": "node", "id": 8517713347, "lat": 47.4320793, "lon": 19.0664992, "tags": {"crossing": "traffic_signals", "crossing:island": "no", "crossing_ref": "zebra", "highway": "crossing", "tactile_paving": "yes"}}, {"type": "node", "id": 8517713348, "lat": 47.4321472, "lon": 19.066567, "tags": {"crossing": "traffic_signals", "crossing:island": "no", "crossing_ref": "zebra", "highway": "crossing", "tactile_paving": "yes"}}, {"type": "node", "id": 8517713349, "lat": 47.4320382, "lon": 19.0664956, "tags": {"highway": "traffic_signals", "traffic_signals": "signal", "traffic_signals:direction": "forward"}}, {"type": "node", "id": 8517713350, "lat": 47.4304745, "lon": 19.0663625, "tags": {"crossing": "traffic_signals", "crossing:island": "no", "crossing_ref": "zebra", "highway": "crossing", "tactile_paving": "yes"}}, {"type": "node", "id": 8517713354, "lat": 47.4304605, "lon": 19.0658288, "tags": {"addr:street": "Teller Ede \u00fat", "button_operated": "yes", "crossing": "traffic_signals", "crossing:island": "no", "crossing_ref": "zebra", "description": "vsb plus", "highway": "traffic_signals", "supervised": "no", "tactile_paving": "yes", "traffic_signals:sound": "yes", "traffic_signals:vibration": "no", "website": "https://www.vgyke.com/hir/eligazodva-a-varosban/"}}, {"type": "node", "id": 8517713355, "lat": 47.430455, "lon": 19.0659695, "tags": {"addr:street": "Teller Ede \u00fat", "button_operated": "yes", "crossing": "traffic_signals", "crossing:island": "no", "crossing_ref": "zebra", "description": "vsb plus", "highway": "traffic_signals", "supervised": "no", "tactile_paving": "yes", "traffic_signals:sound": "yes", "traffic_signals:vibration": "no", "website": "https://www.vgyke.com/hir/eligazodva-a-varosban/"}}, {"type": "node", "id": 8517713356, "lat": 47.4306801, "lon": 19.0658555, "tags": {"addr:street": "Teller Ede \u00fat", "button_operated": "yes", "crossing": "traffic_signals", "crossing:island": "no", "crossing_ref": "zebra", "description": "vsb plus", "highway": "traffic_signals", "supervised": "no", "tactile_paving": "yes", "traffic_signals:sound": "yes", "traffic_signals:vibration": "no", "website": "https://www.vgyke.com/hir/eligazodva-a-varosban/"}}, {"type": "node", "id": 8517713357, "lat": 47.4306712, "lon": 19.0660075, "tags": {"addr:street": "Teller Ede \u00fat", "button_operated": "yes", "crossing": "traffic_signals", "crossing:island": "no", "crossing_ref": "zebra", "description": "vsb plus", "highway": "traffic_signals", "supervised": "no", "tactile_paving": "yes", "traffic_signals:sound": "yes", "traffic_signals:vibration": "no", "website": "https://www.vgyke.com/hir/eligazodva-a-varosban/"}}, {"type": "node", "id": 8517713358, "lat": 47.4305926, "lon": 19.0656207, "tags": {"crossing": "traffic_signals", "crossing:island": "no", "crossing_ref": "zebra", "highway": "crossing", "tactile_paving": "yes"}}, {"type": "node", "id": 8517725325, "lat": 47.4238325, "lon": 19.0632361, "tags": {"addr:street": "Teller Ede \u00fat", "button_operated": "yes", "crossing": "traffic_signals", "crossing:island": "yes", "crossing_ref": "zebra", "description": "vsb plus", "highway": "traffic_signals", "supervised": "no", "tactile_paving": "yes", "traffic_signals:sound": "yes", "traffic_signals:vibration": "no", "website": "https://www.vgyke.com/hir/eligazodva-a-varosban/"}}, {"type": "node", "id": 8517725326, "lat": 47.4237997, "lon": 19.0633676, "tags": {"addr:street": "Teller Ede \u00fat", "button_operated": "yes", "crossing": "traffic_signals", "crossing:island": "yes", "crossing_ref": "zebra", "description": "vsb plus", "highway": "traffic_signals", "supervised": "no", "tactile_paving": "yes", "traffic_signals:sound": "yes", "traffic_signals:vibration": "no", "website": "https://www.vgyke.com/hir/eligazodva-a-varosban/"}}, {"type": "node", "id": 8517725327, "lat": 47.4237504, "lon": 19.0633391, "tags": {"highway": "traffic_signals", "traffic_signals": "signal", "traffic_signals:direction": "forward"}}, {"type": "node", "id": 8517725328, "lat": 47.4239419, "lon": 19.0632935, "tags": {"highway": "traffic_signals", "traffic_signals": "signal", "traffic_signals:direction": "forward"}}, {"type": "node", "id": 8517725329, "lat": 47.4238524, "lon": 19.0635963, "tags": {"highway": "traffic_signals", "traffic_signals": "signal", "traffic_signals:direction": "forward"}}, {"type": "node", "id": 8517725330, "lat": 47.4235884, "lon": 19.0648285, "tags": {"direction": "backward", "highway": "give_way"}}, {"type": "node", "id": 8517725331, "lat": 47.4234548, "lon": 19.0647559, "tags": {"direction": "forward", "highway": "give_way"}}, {"type": "node", "id": 8517725332, "lat": 47.4221592, "lon": 19.0623638, "tags": {"highway": "traffic_signals", "traffic_signals": "signal", "traffic_signals:direction": "forward"}}, {"type": "node", "id": 9028088452, "lat": 47.4269679, "lon": 19.0647849, "tags": {"addr:street": "Kar\u00e1csony S\u00e1ndor utca", "crossing": "traffic_signals", "crossing_ref": "zebra", "highway": "crossing", "supervised": "no", "tactile_paving": "yes", "traffic_signals:sound": "yes", "traffic_signals:vibration": "no", "website": "https://www.vgyke.com/hir/eligazodva-a-varosban/"}}, {"type": "node", "id": 9028088453, "lat": 47.426843, "lon": 19.0650116, "tags": {"addr:street": "Teller Ede \u00fat", "crossing": "traffic_signals", "crossing_ref": "zebra", "description": "vsb plus", "highway": "traffic_signals", "supervised": "no", "tactile_paving": "yes", "traffic_signals:sound": "yes", "traffic_signals:vibration": "no", "website": "https://www.vgyke.com/hir/eligazodva-a-varosban/"}}, {"type": "node", "id": 9028088454, "lat": 47.4268437, "lon": 19.064868, "tags": {"addr:street": "Teller Ede \u00fat", "crossing": "traffic_signals", "crossing_ref": "zebra", "description": "vsb plus", "highway": "traffic_signals", "supervised": "no", "tactile_paving": "yes", "traffic_signals:sound": "yes", "traffic_signals:vibration": "no", "website": "https://www.vgyke.com/hir/eligazodva-a-varosban/"}}, {"type": "node", "id": 9028088455, "lat": 47.4270956, "lon": 19.064998, "tags": {"addr:street": "Teller Ede \u00fat", "crossing": "traffic_signals", "crossing_ref": "zebra", "description": "vsb plus", "highway": "traffic_signals", "supervised": "no", "tactile_paving": "yes", "traffic_signals:sound": "yes", "traffic_signals:vibration": "no", "website": "https://www.vgyke.com/hir/eligazodva-a-varosban/"}}, {"type": "node", "id": 9028088456, "lat": 47.4270887, "lon": 19.0651388, "tags": {"addr:street": "Teller Ede \u00fat", "crossing": "traffic_signals", "crossing_ref": "zebra", "description": "vsb plus", "highway": "traffic_signals", "supervised": "no", "tactile_paving": "yes", "traffic_signals:sound": "yes", "traffic_signals:vibration": "no", "website": "https://www.vgyke.com/hir/eligazodva-a-varosban/"}}, {"type": "node", "id": 9208321222, "lat": 47.425012, "lon": 19.0699538, "tags": {"crossing": "marked", "crossing:island": "yes", "highway": "crossing", "tactile_paving": "yes"}}, {"type": "node", "id": 9208322624, "lat": 47.4247435, "lon": 19.0694019, "tags": {"traffic_calming": "bump"}}, {"type": "node", "id": 9208322625, "lat": 47.4250633, "lon": 19.0694304, "tags": {"traffic_calming": "bump"}}, {"type": "node", "id": 9208322626, "lat": 47.4246836, "lon": 19.0694974, "tags": {"traffic_calming": "table"}}, {"type": "node", "id": 9208322629, "lat": 47.4249773, "lon": 19.0697793, "tags": {"traffic_calming": "table"}}, {"type": "node", "id": 9208322634, "lat": 47.4250785, "lon": 19.0694318}, {"type": "node", "id": 9208322637, "lat": 47.4250073, "lon": 19.0697558}, {"type": "node", "id": 9362789248, "lat": 47.4300801, "lon": 19.0663265}, {"type": "node", "id": 9482792956, "lat": 47.4283321, "lon": 19.0702271}, {"type": "node", "id": 9623407295, "lat": 47.4310433, "lon": 19.0716639}, {"type": "way", "id": 10222778, "nodes": [527360241, 2286686288, 2576631909, 527360240], "tags": {"highway": "residential", "lcn": "proposed", "lit": "yes", "name": "K\u00e1roli G\u00e1sp\u00e1r utca", "surface": "asphalt"}}, {"type": "way", "id": 10222842, "nodes": [84694657, 84693705, 1020424278, 244926008], "tags": {"highway": "residential", "lcn": "proposed", "lit": "yes", "name": "Vermes Mikl\u00f3s utca", "old_name": "Kolt\u00f3i Anna utca", "sidewalk": "no", "source:name": "http://einfoszab.budapest.hu/list/fovarosi-kozgyules-nyilvanos-ulesei;parenttype=2;parentid=6095;type=3;id=79357", "surface": "asphalt"}}, {"type": "way", "id": 25870539, "nodes": [281868324, 1704215394, 1704215397, 1704215400, 1704207815, 1704207824, 1704207847, 1704207795, 1704207840, 282197548], "tags": {"highway": "residential", "lcn": "proposed", "lit": "yes", "name": "\u00c1rp\u00e1d utca", "surface": "asphalt"}}, {"type": "way", "id": 25870767, "nodes": [527360252, 2235432675, 527360259, 527360263, 282197417], "tags": {"highway": "residential", "lit": "yes", "name": "V\u00e1g\u00f3h\u00edd utca", "surface": "asphalt"}}, {"type": "way", "id": 32884229, "nodes": [244926008, 1319217238, 3038589658, 546926138, 6190798621], "tags": {"highway": "tertiary", "lanes": "2", "lcn": "proposed", "name": "Szent Imre t\u00e9r", "old_name": "Kolt\u00f3i Anna utca", "oneway": "yes", "source:name": "http://einfoszab.budapest.hu/list/fovarosi-kozgyules-nyilvanos-ulesei;parenttype=2;parentid=6095;type=3;id=79357", "surface": "asphalt"}}, {"type": "way", "id": 32884236, "nodes": [84690999, 1319217117, 3545111611, 3545111610, 2145731902, 2145731906, 514817230], "tags": {"highway": "tertiary", "lanes": "3", "lanes:backward": "1", "lanes:forward": "2", "lcn": "proposed", "name": "K\u00e1roli G\u00e1sp\u00e1r utca", "surface": "asphalt", "turn:lanes:backward": "slight_right", "turn:lanes:forward": "slight_left;through|slight_right;right"}}, {"type": "way", "id": 41769951, "nodes": [546926163, 2235248070, 2217275302, 282198529, 2217268375, 3038589664, 282196265, 2235270179, 154480703], "tags": {"highway": "tertiary", "lanes": "2", "name": "T\u00e1ncsics Mih\u00e1ly utca", "surface": "asphalt"}}, {"type": "way", "id": 41770350, "nodes": [2160949504, 5139243118, 1020419184, 1319217255, 84694657], "tags": {"highway": "residential", "lcn": "proposed", "name": "II. R\u00e1k\u00f3czi Ferenc \u00fat", "oneway": "yes", "surface": "asphalt"}}, {"type": "way", "id": 41770449, "nodes": [1876545354, 2149954114], "tags": {"highway": "residential", "lit": "yes", "name": "Vermes Mikl\u00f3s utca", "old_name": "Kolt\u00f3i Anna utca", "surface": "asphalt"}}, {"type": "way", "id": 41771898, "nodes": [514868748, 1945984555, 1945984557, 2576613482, 653971333, 2520714034, 514869167], "tags": {"highway": "residential", "lit": "yes", "name": "Erd\u00e9lyi utca", "surface": "asphalt"}}, {"type": "way", "id": 42278765, "nodes": [84693632, 2129797006, 1319179790], "tags": {"highway": "tertiary", "lanes": "2", "lcn": "proposed", "name": "K\u00e1roli G\u00e1sp\u00e1r utca", "surface": "asphalt"}}, {"type": "way", "id": 42278766, "nodes": [527360242, 2235270175, 2235270170, 527360258, 527360243, 527360244], "tags": {"highway": "residential", "lit": "yes", "name": "De\u00e1k Ferenc utca", "surface": "asphalt"}}, {"type": "way", "id": 42278767, "nodes": [527360248, 2277543808, 527360260, 527360249, 527360250, 527360251], "tags": {"highway": "residential", "name": "\u00cdv utca", "surface": "asphalt"}}, {"type": "way", "id": 42278770, "nodes": [527360262, 527360263], "tags": {"highway": "residential", "lit": "yes", "name": "Pozsonyi utca", "sidewalk": "both", "surface": "asphalt"}}, {"type": "way", "id": 42278771, "nodes": [527360264, 2286718413, 3038589651, 514869167, 3038589649, 527360265, 2286708328], "tags": {"highway": "residential", "name": "J\u00f3zsef Attila utca", "surface": "asphalt"}}, {"type": "way", "id": 43403200, "nodes": [546925892, 546925894, 546925896, 9028088452, 1876545353, 2129804865], "tags": {"highway": "tertiary", "lanes": "3", "lanes:backward": "1", "lanes:forward": "2", "lit": "yes", "name": "Kar\u00e1csony S\u00e1ndor utca", "surface": "asphalt", "turn:lanes:backward": "through", "turn:lanes:forward": "slight_left|through;right"}}, {"type": "way", "id": 43403216, "nodes": [546926138, 1425843611, 3038589660, 3038589662, 546926140, 546926151, 2121174315, 2121174318], "tags": {"highway": "residential", "name": "Templom utca"}}, {"type": "way", "id": 43403217, "nodes": [546926140, 546926142, 546926144, 546926145, 546926146, 546926147, 546926148, 546926149, 546926150, 546926151], "tags": {"highway": "residential"}}, {"type": "way", "id": 43403218, "nodes": [546926152, 546926154], "tags": {"highway": "residential", "maxspeed": "30", "name": "Kiss J\u00e1nos alt\u00e1bornagy utca"}}, {"type": "way", "id": 43403220, "nodes": [154480703, 2239750881, 527360242, 2235270162, 84693632], "tags": {"highway": "tertiary", "lanes": "2", "name": "T\u00e1ncsics Mih\u00e1ly utca", "surface": "asphalt"}}, {"type": "way", "id": 43403232, "nodes": [546926222, 2077721406, 2321776720, 2150875425, 2321776724, 9208322624, 2119558410, 2321776718, 9208322625, 9208322634, 546926224], "tags": {"bicycle": "destination", "highway": "living_street", "maxspeed": "5", "motor_vehicle": "destination", "noname": "yes", "surface": "asphalt"}}, {"type": "way", "id": 43403237, "nodes": [546925885, 2281481717, 1319852150], "tags": {"highway": "tertiary", "name": "Mansfeld P\u00e9ter utca", "surface": "asphalt"}}, {"type": "way", "id": 43403238, "nodes": [546926236, 2026341876, 2026341879, 546926237, 1020423845], "tags": {"highway": "residential", "lit": "yes", "name": "Magash\u00e1zy utca", "old_name": "L\u00e1ng K\u00e1lm\u00e1n utca", "sidewalk": "no", "source:name": "http://einfoszab.budapest.hu/list/fovarosi-kozgyules-nyilvanos-ulesei;parenttype=2;parentid=6340;type=3;id=83213", "surface": "paving_stones"}}, {"type": "way", "id": 54118641, "nodes": [84687274, 1319180110], "tags": {"highway": "tertiary", "lanes": "2", "lcn": "proposed", "name": "Vermes Mikl\u00f3s utca", "old_name": "Kolt\u00f3i Anna utca", "oneway": "yes", "source:name": "http://einfoszab.budapest.hu/list/fovarosi-kozgyules-nyilvanos-ulesei;parenttype=2;parentid=6095;type=3;id=79357", "surface": "asphalt"}}, {"type": "way", "id": 54118644, "nodes": [84690999, 1020418813, 1877833308], "tags": {"highway": "tertiary", "lane_markings": "no", "lcn": "proposed", "name": "II. R\u00e1k\u00f3czi Ferenc \u00fat", "oneway": "yes", "surface": "asphalt"}}, {"type": "way", "id": 54118645, "nodes": [244926008, 1319217249, 2982089896, 3038589667, 3038589669, 546926131, 2121206482, 1020420490, 1318819101, 1319852165], "tags": {"access": "yes", "bus": "no", "highway": "residential", "lcn": "proposed", "name": "II. R\u00e1k\u00f3czi Ferenc \u00fat", "oneway": "yes", "surface": "asphalt"}}, {"type": "way", "id": 54118646, "nodes": [84693633, 1319179795, 2278318294, 2026329310, 2278318296, 1319217109, 244926007], "tags": {"highway": "tertiary", "lanes": "2", "lcn": "proposed", "name": "Szent Imre t\u00e9r", "oneway": "yes", "surface": "asphalt"}}, {"type": "way", "id": 87763474, "nodes": [1020421741, 1020420984, 1020419089, 1020425922, 1020423845], "tags": {"highway": "residential", "noname": "yes"}}, {"type": "way", "id": 115954015, "nodes": [514832798, 2324415272, 514832801, 2324415275, 514832805, 320654003, 1413108012, 2324415278, 1413108033, 1413107986, 1413107957, 320653544], "tags": {"highway": "tertiary", "name": "K\u00f6zponti \u00fat"}}, {"type": "way", "id": 117104937, "nodes": [546926154, 2150893322, 1319180072], "tags": {"access": "yes", "highway": "residential", "lcn": "proposed", "name": "Kiss J\u00e1nos alt\u00e1bornagy utca", "oneway": "yes", "surface": "asphalt"}}, {"type": "way", "id": 117172468, "nodes": [2324415268, 4690584499, 2324415270, 514832798], "tags": {"highway": "tertiary", "motor_vehicle": "destination", "name": "D\u00e9li utca"}}, {"type": "way", "id": 117337695, "nodes": [514817230, 2145731914, 2954141053, 8517713349, 8517713347, 2113685778, 514817227], "tags": {"highway": "residential", "lit": "yes", "name": "Cs\u0151gy\u00e1r utca", "oneway": "yes", "surface": "asphalt"}}, {"type": "way", "id": 117337700, "nodes": [244926007, 1020419650, 3385709535], "tags": {"highway": "tertiary", "lanes": "2", "lcn": "proposed", "name": "Szent Imre t\u00e9r", "oneway": "yes", "surface": "asphalt"}}, {"type": "way", "id": 117337701, "nodes": [1020420024, 546925898], "tags": {"highway": "tertiary", "lane_markings": "no", "lcn": "proposed", "name": "II. R\u00e1k\u00f3czi Ferenc \u00fat", "oneway": "yes", "surface": "asphalt"}}, {"type": "way", "id": 117337705, "nodes": [546926154, 2144602474, 2150893324, 154480703], "tags": {"highway": "tertiary", "name": "Vermes Mikl\u00f3s utca", "old_name": "Kolt\u00f3i Anna utca", "oneway": "yes", "source:name": "http://einfoszab.budapest.hu/list/fovarosi-kozgyules-nyilvanos-ulesei;parenttype=2;parentid=6095;type=3;id=79357", "surface": "asphalt"}}, {"type": "way", "id": 117337716, "nodes": [1319179790, 3375747175], "tags": {"highway": "tertiary", "lane_markings": "no", "lcn": "proposed", "lit": "yes", "name": "K\u00e1roli G\u00e1sp\u00e1r utca", "oneway": "yes", "surface": "asphalt"}}, {"type": "way", "id": 117337717, "nodes": [244926007, 1020421208, 1020422006, 84690999], "tags": {"highway": "tertiary", "lcn": "proposed", "name": "K\u00e1roli G\u00e1sp\u00e1r utca", "oneway": "yes", "surface": "asphalt"}}, {"type": "way", "id": 117337722, "nodes": [1319852150, 1319852152, 546925888, 546925890, 546925892], "tags": {"highway": "tertiary", "name": "Mansfeld P\u00e9ter utca", "old_name": "Baj\u00e1ki Ferenc utca"}}, {"type": "way", "id": 117337733, "nodes": [1877785773, 2324415283, 2576852984, 1877819070, 320653544], "tags": {"highway": "tertiary", "motor_vehicle": "destination", "name": "Sz\u00ednesf\u00e9m utca"}}, {"type": "way", "id": 117337734, "nodes": [84693632, 2129797000, 527360248, 2235432678, 527360252], "tags": {"highway": "tertiary", "lanes": "2", "lcn": "proposed", "name": "T\u00e1ncsics Mih\u00e1ly utca", "surface": "asphalt"}}, {"type": "way", "id": 117337735, "nodes": [2319944142, 2967566762, 2286718429, 527360264, 2286718395, 8111199653, 546926199, 2281983977, 2281983975, 2281983974, 2267377547, 367657132], "tags": {"highway": "tertiary", "lanes": "2", "name": "T\u00e1ncsics Mih\u00e1ly utca", "surface": "asphalt"}}, {"type": "way", "id": 117337744, "nodes": [1319180072, 9623407295, 1319179812], "tags": {"access": "yes", "highway": "residential", "lcn": "proposed", "name": "Kiss J\u00e1nos alt\u00e1bornagy utca", "oneway": "yes", "surface": "asphalt"}}, {"type": "way", "id": 117337748, "nodes": [1319179812, 2239807000, 1319179790], "tags": {"access": "yes", "highway": "residential", "lcn": "proposed", "name": "Kiss J\u00e1nos alt\u00e1bornagy utca", "oneway": "yes", "surface": "asphalt"}}, {"type": "way", "id": 127730551, "nodes": [1413107975, 1413107923, 1413107970, 4157766784], "tags": {"highway": "residential", "name": "Vas\u00fat sor", "source": "Bing"}}, {"type": "way", "id": 177146224, "nodes": [514817227, 1319217246, 2160949531, 320651986, 8517696598, 546926082], "tags": {"highway": "residential", "name": "Cs\u0151gy\u00e1r utca", "oneway": "yes"}}, {"type": "way", "id": 177295426, "nodes": [2281481736, 1877833317, 546926233, 1877833327, 2281481742], "tags": {"highway": "residential", "name": "Magyar utca", "oneway": "yes", "surface": "asphalt"}}, {"type": "way", "id": 177295676, "nodes": [546925981, 1412912008, 6003113895, 6003113896, 6003113897, 6003113898, 546925972], "tags": {"highway": "residential", "maxweight:hgv": "12", "name": "Pet\u0151fi utca"}}, {"type": "way", "id": 177332316, "nodes": [2281481715, 6190442829, 1877833306, 1877833319, 2281481730], "tags": {"highway": "residential", "lane_markings": "no", "lit": "yes", "maxspeed": "40", "name": "Magyar utca", "oneway": "yes", "surface": "asphalt"}}, {"type": "way", "id": 177332317, "nodes": [546926238, 546926239, 546926240, 546926241, 9362789248, 2145731888, 8517713350, 514817230], "tags": {"highway": "residential", "lanes": "2", "name": "Magash\u00e1zy utca", "old_name": "L\u00e1ng K\u00e1lm\u00e1n utca", "oneway": "yes", "source:name": "http://einfoszab.budapest.hu/list/fovarosi-kozgyules-nyilvanos-ulesei;parenttype=2;parentid=6340;type=3;id=83213"}}, {"type": "way", "id": 177332318, "nodes": [6190400270, 546925962, 6900286794, 2026341868, 1020420024], "tags": {"highway": "residential", "lcn": "proposed", "name": "Kar\u00e1csony S\u00e1ndor utca"}}, {"type": "way", "id": 178915430, "nodes": [2171619784, 2165192534, 2165192538, 2129792938, 2026329307, 3569374498], "tags": {"cycleway:both": "lane", "cycleway:both:lane": "advisory", "highway": "tertiary", "lcn": "yes", "name": "Kossuth Lajos utca", "smoothness": "excellent", "surface": "asphalt"}}, {"type": "way", "id": 178915432, "nodes": [6190798620, 3090564035, 2325474715, 7945906613, 2195737929, 2259953795, 6190798619], "tags": {"cycleway:left": "lane", "highway": "tertiary", "lcn": "yes", "name": "Kossuth Lajos utca", "surface": "asphalt"}}, {"type": "way", "id": 178915433, "nodes": [84687274, 1319180095, 2113696903, 6190798622], "tags": {"cycleway": "lane", "highway": "tertiary", "lanes": "3", "lanes:backward": "2", "lanes:forward": "1", "lcn": "yes", "name": "Szent Imre t\u00e9r", "smoothness": "excellent", "surface": "asphalt", "turn:lanes:backward": "through|right", "turn:lanes:forward": "through"}}, {"type": "way", "id": 178915436, "nodes": [514817230, 2244819769], "tags": {"highway": "tertiary", "lanes": "3", "lanes:backward": "1", "lanes:forward": "2", "lcn": "proposed", "lit": "yes", "name": "K\u00e1roli G\u00e1sp\u00e1r utca", "surface": "asphalt", "turn:lanes:backward": "left;through", "turn:lanes:forward": "slight_left;through|slight_right"}}, {"type": "way", "id": 178915441, "nodes": [514817227, 8517713348, 2149954018, 3371431012], "tags": {"highway": "residential", "lanes": "3", "lanes:backward": "2", "lanes:forward": "1", "lcn": "proposed", "lit": "yes", "name": "Vermes Mikl\u00f3s utca", "old_name": "Kolt\u00f3i Anna utca", "source:name": "http://einfoszab.budapest.hu/list/fovarosi-kozgyules-nyilvanos-ulesei;parenttype=2;parentid=6095;type=3;id=79357", "surface": "asphalt", "turn:lanes:backward": "through|slight_right;right"}}, {"type": "way", "id": 192076504, "nodes": [2026329309, 2132914720, 2026329308, 2124795081, 2060239364, 2026329307], "tags": {"highway": "residential", "maxspeed": "30", "oneway": "yes", "zone:maxspeed": "HU:30"}}, {"type": "way", "id": 192076505, "nodes": [2026329310, 2041821193, 2303381776, 2303381774, 2026329309, 2056021561, 2132914713, 1319852158], "tags": {"highway": "residential", "maxspeed": "30", "name": "Petz Ferenc utca", "zone:maxspeed": "HU:30"}}, {"type": "way", "id": 192077822, "nodes": [2026329302, 2052435209, 2052435207, 2052435205, 2052435202, 2046242006, 2052435200, 2149955676, 2046242001], "tags": {"highway": "residential", "maxspeed": "30", "zone:maxspeed": "HU:30"}}, {"type": "way", "id": 194113008, "nodes": [2060235382, 2046242006], "tags": {"highway": "residential", "maxspeed": "30", "zone:maxspeed": "HU:30"}}, {"type": "way", "id": 205117036, "nodes": [2150875425, 9208322626, 2150875423, 2150875424, 2150875426, 9208322629, 9208322637, 2150875427], "tags": {"highway": "living_street", "lanes": "1", "lit": "yes", "maxspeed": "5", "noname": "yes", "oneway": "yes", "surface": "paving_stones"}}, {"type": "way", "id": 207770499, "nodes": [84694657, 1020424125, 1020420068, 2281111500, 84690999], "tags": {"highway": "residential", "lanes": "1", "lcn": "proposed", "lit": "yes", "name": "Szent Imre t\u00e9r", "oneway": "yes", "surface": "asphalt"}}, {"type": "way", "id": 207770500, "nodes": [1877833308, 546926236], "tags": {"highway": "tertiary", "lane_markings": "no", "lcn": "proposed", "name": "II. R\u00e1k\u00f3czi Ferenc \u00fat", "oneway": "yes", "surface": "asphalt"}}, {"type": "way", "id": 208022635, "nodes": [244929127, 2286708352], "tags": {"highway": "residential", "lcn": "proposed", "name": "Katona J\u00f3zsef utca", "oneway": "no", "surface": "asphalt"}}, {"type": "way", "id": 214433747, "nodes": [282197548, 2576631912, 527360243, 2526611642, 2576631911, 527360240], "tags": {"highway": "residential", "lcn": "proposed", "lit": "yes", "name": "Bajcsy-Zsilinszky \u00fat", "surface": "asphalt"}}, {"type": "way", "id": 218597315, "nodes": [546926236, 1020424161, 1020420024], "tags": {"highway": "tertiary", "lane_markings": "no", "lcn": "proposed", "name": "II. R\u00e1k\u00f3czi Ferenc \u00fat", "oneway": "yes", "surface": "asphalt"}}, {"type": "way", "id": 218597316, "nodes": [1020423845, 2041929911], "tags": {"highway": "residential", "name": "Magash\u00e1zy utca", "old_name": "L\u00e1ng K\u00e1lm\u00e1n utca", "source:name": "http://einfoszab.budapest.hu/list/fovarosi-kozgyules-nyilvanos-ulesei;parenttype=2;parentid=6340;type=3;id=83213"}}, {"type": "way", "id": 218949608, "nodes": [2281481734, 6190442836, 1877488587], "tags": {"highway": "secondary", "lanes": "2", "name": "Bet\u0171 utca", "oneway": "yes", "surface": "asphalt"}}, {"type": "way", "id": 218949609, "nodes": [1877488588, 6190442834, 8517725329, 2281481733, 2281481734], "tags": {"cycleway:right": "no", "highway": "secondary", "lanes": "3", "name": "Bet\u0171 utca", "oneway": "yes", "surface": "asphalt", "turn:lanes": "left|right|right"}}, {"type": "way", "id": 218949610, "nodes": [546925969, 2281481727, 546925981, 6152675751, 6152675750, 546925964], "tags": {"cycleway:right": "no", "highway": "secondary", "lanes": "2", "name": "Bet\u0171 utca", "oneway": "yes", "surface": "asphalt"}}, {"type": "way", "id": 218949621, "nodes": [1876545354, 8517713342, 8517713356, 1876545352], "tags": {"highway": "secondary", "lanes": "3", "name": "Teller Ede \u00fat", "oneway": "yes", "surface": "asphalt", "turn:lanes": "left|through|through;right"}}, {"type": "way", "id": 218949622, "nodes": [2145731910, 8517713357, 2281481761], "tags": {"highway": "secondary", "lanes": "2", "name": "Teller Ede \u00fat", "oneway": "yes", "surface": "asphalt"}}, {"type": "way", "id": 218949623, "nodes": [1876545352, 8517713354, 2582084284, 2582084283, 1876545356], "tags": {"highway": "secondary", "lanes": "2", "name": "Teller Ede \u00fat", "oneway": "yes", "surface": "asphalt"}}, {"type": "way", "id": 218949624, "nodes": [2281481732, 8517725332, 4886079016, 1876545358], "tags": {"cycleway:right": "track", "highway": "secondary", "lanes": "3", "name": "Teller Ede \u00fat", "oneway": "yes", "surface": "asphalt", "turn:lanes": "left|left|right"}}, {"type": "way", "id": 218949625, "nodes": [2281481775, 8517713340, 1876545354], "tags": {"highway": "secondary", "lanes": "3", "name": "Teller Ede \u00fat", "oneway": "yes", "surface": "asphalt", "turn:lanes": "left|through|through"}}, {"type": "way", "id": 218949626, "nodes": [2281481774, 2281481781, 8517696597, 2281481786], "tags": {"highway": "secondary", "lanes": "3", "name": "Teller Ede \u00fat", "oneway": "yes", "surface": "asphalt", "turn:lanes": "left|through|through;right"}}, {"type": "way", "id": 218949627, "nodes": [2281481740, 2281481742, 9028088453, 2129804865], "tags": {"highway": "secondary", "lanes": "3", "name": "Teller Ede \u00fat", "oneway": "yes", "turn:lanes": "left|through|through;right"}}, {"type": "way", "id": 218949628, "nodes": [2281481755, 2281481756, 8517713355, 2145731910], "tags": {"highway": "secondary", "lanes": "3", "name": "Teller Ede \u00fat", "oneway": "yes", "turn:lanes": "left|through|through;right"}}, {"type": "way", "id": 218949630, "nodes": [2149954114, 8517713341, 2281481772, 2281481773, 2281481774], "tags": {"highway": "secondary", "lanes": "2", "name": "Teller Ede \u00fat", "oneway": "yes"}}, {"type": "way", "id": 218949631, "nodes": [1876545361, 1876545355, 2281481776, 2281481775], "tags": {"highway": "secondary", "lanes": "2", "name": "Teller Ede \u00fat", "oneway": "yes", "surface": "asphalt"}}, {"type": "way", "id": 218949632, "nodes": [2281481761, 2281481763, 2281481764, 2281481765, 8517713343, 2149954114], "tags": {"highway": "secondary", "lanes": "3", "name": "Teller Ede \u00fat", "oneway": "yes", "surface": "asphalt", "turn:lanes": "through|through|right"}}, {"type": "way", "id": 218949634, "nodes": [1876545356, 2281481753, 2281481751, 1876545357, 9028088455, 1876545353], "tags": {"highway": "secondary", "lanes": "3", "name": "Teller Ede \u00fat", "oneway": "yes", "turn:lanes": "left|through|through;right"}}, {"type": "way", "id": 218949635, "nodes": [2129804865, 9028088456, 2281481750, 2281481752, 2281481754, 2281481755], "tags": {"highway": "secondary", "lanes": "2", "name": "Teller Ede \u00fat", "oneway": "yes"}}, {"type": "way", "id": 218949636, "nodes": [1876545353, 9028088454, 1876545360, 1876545362, 1877833313, 8517725328, 1877488587, 8517725325, 2281481732], "tags": {"highway": "secondary", "lanes": "2", "name": "Teller Ede \u00fat", "oneway": "yes", "surface": "asphalt", "turn:lanes": "through|through"}}, {"type": "way", "id": 218949637, "nodes": [546925956, 2281481712, 2281481715, 2281481718, 2281481730, 8517725327, 8517725326, 2281481734, 2281481736, 2281481740], "tags": {"cycleway:right": "lane", "cycleway:right:lane": "exclusive", "highway": "secondary", "lanes": "2", "name": "Teller Ede \u00fat", "oneway": "yes", "surface": "asphalt", "turn:lanes": "through|through"}}, {"type": "way", "id": 219521872, "nodes": [244929128, 2286708348, 2286708338, 2967537737, 3038589653, 2286708336, 2286718407, 527360265], "tags": {"highway": "residential", "lcn": "proposed", "lit": "yes", "name": "Bajcsy-Zsilinszky \u00fat", "surface": "asphalt"}}, {"type": "way", "id": 219521874, "nodes": [2286708352, 2286708353, 2286708354, 244929128], "tags": {"highway": "residential", "lcn": "proposed", "name": "Katona J\u00f3zsef utca", "oneway": "no", "surface": "asphalt"}}, {"type": "way", "id": 223556658, "nodes": [1413107923, 2324415266, 2324415267], "tags": {"highway": "residential", "name": "K\u00f3rh\u00e1z k\u00f6z"}}, {"type": "way", "id": 240552107, "nodes": [527360252, 546925910], "tags": {"highway": "tertiary", "lanes": "2", "lcn": "proposed", "name": "T\u00e1ncsics Mih\u00e1ly utca", "surface": "asphalt"}}, {"type": "way", "id": 251469134, "nodes": [2324415267, 2324415269], "tags": {"highway": "residential", "name": "Kert utca"}}, {"type": "way", "id": 252092256, "nodes": [2582084286, 2582084289, 2113794533, 2113794589, 1319852153], "tags": {"highway": "tertiary", "name": "II. R\u00e1k\u00f3czi Ferenc \u00fat", "oneway": "yes", "surface": "asphalt"}}, {"type": "way", "id": 267364223, "nodes": [2041929910, 546926238, 2139223130, 2026341883, 2026341881, 2139223129, 1319217100, 1877833308], "tags": {"highway": "residential", "name": "Magash\u00e1zy utca", "old_name": "L\u00e1ng K\u00e1lm\u00e1n utca", "source:name": "http://einfoszab.budapest.hu/list/fovarosi-kozgyules-nyilvanos-ulesei;parenttype=2;parentid=6340;type=3;id=83213"}}, {"type": "way", "id": 302403506, "nodes": [3066608649, 244929127], "tags": {"highway": "residential", "lit": "yes", "name": "Kolozsv\u00e1ri utca", "surface": "asphalt"}}, {"type": "way", "id": 314664219, "nodes": [2145731910, 1876545352], "tags": {"highway": "tertiary", "lit": "yes", "name": "K\u00e1roli G\u00e1sp\u00e1r utca", "surface": "asphalt"}}, {"type": "way", "id": 314664220, "nodes": [1876545352, 8517713358, 84693635], "tags": {"highway": "tertiary", "lit": "yes", "name": "K\u00e1roli G\u00e1sp\u00e1r utca", "surface": "asphalt"}}, {"type": "way", "id": 314664229, "nodes": [2149954114, 2244819882], "tags": {"highway": "residential", "lanes": "3", "lanes:backward": "2", "lanes:forward": "1", "lit": "yes", "name": "Vermes Mikl\u00f3s utca", "old_name": "Kolt\u00f3i Anna utca", "source:name": "http://einfoszab.budapest.hu/list/fovarosi-kozgyules-nyilvanos-ulesei;parenttype=2;parentid=6095;type=3;id=79357", "surface": "asphalt", "turn:lanes:backward": "slight_left|slight_right"}}, {"type": "way", "id": 314853469, "nodes": [2235427917, 244929129], "tags": {"highway": "residential", "lcn": "proposed", "lit": "yes", "name": "Katona J\u00f3zsef utca", "oneway": "no", "surface": "asphalt"}}, {"type": "way", "id": 330190459, "nodes": [3371431012, 3371431011], "tags": {"highway": "residential", "lcn": "proposed", "name": "Vermes Mikl\u00f3s utca", "old_name": "Kolt\u00f3i Anna utca", "source:name": "http://einfoszab.budapest.hu/list/fovarosi-kozgyules-nyilvanos-ulesei;parenttype=2;parentid=6095;type=3;id=79357", "surface": "asphalt"}}, {"type": "way", "id": 330190460, "nodes": [3371431011, 1319217240, 84694657], "tags": {"highway": "residential", "lcn": "proposed", "name": "Vermes Mikl\u00f3s utca", "old_name": "Kolt\u00f3i Anna utca", "source:name": "http://einfoszab.budapest.hu/list/fovarosi-kozgyules-nyilvanos-ulesei;parenttype=2;parentid=6095;type=3;id=79357", "surface": "asphalt"}}, {"type": "way", "id": 330596249, "nodes": [3375747175, 2113696882, 1319179793, 84693633], "tags": {"highway": "tertiary", "lanes": "3", "lcn": "proposed", "lit": "yes", "name": "K\u00e1roli G\u00e1sp\u00e1r utca", "oneway": "yes", "surface": "asphalt", "turn:lanes": "left|through|right"}}, {"type": "way", "id": 331495835, "nodes": [3385709535, 2139223133, 1020423511, 244926008], "tags": {"highway": "tertiary", "lanes": "2", "lcn": "proposed", "name": "Szent Imre t\u00e9r", "oneway": "yes", "surface": "asphalt"}}, {"type": "way", "id": 351199255, "nodes": [3569374498, 546925948, 2113696874, 1319179771, 84693633], "tags": {"cycleway:both": "lane", "cycleway:both:lane": "exclusive", "highway": "tertiary", "lanes": "3", "lanes:backward": "1", "lanes:forward": "2", "lcn": "yes", "name": "Kossuth Lajos utca", "smoothness": "excellent", "surface": "asphalt", "turn:lanes:backward": "through", "turn:lanes:forward": "left|through"}}, {"type": "way", "id": 351199256, "nodes": [2153340901, 2169116304, 84689061, 2169116309, 546926192, 2169116313, 7945906614, 9208321222, 546926232, 2149571480, 2169116325, 2169116328, 546925903, 2038247255, 2038247256, 9482792956, 2026329303, 2171619784], "tags": {"cycleway:both": "lane", "cycleway:both:lane": "advisory", "highway": "tertiary", "lanes": "2", "lcn": "yes", "name": "Kossuth Lajos utca", "smoothness": "excellent", "surface": "asphalt"}}, {"type": "way", "id": 384337678, "nodes": [3876392078, 3876392077], "tags": {"cycleway:both": "no", "highway": "tertiary", "lanes": "3", "lanes:backward": "1", "lanes:forward": "2", "lcn": "yes", "name": "Szent Imre t\u00e9r", "smoothness": "excellent", "surface": "asphalt"}}, {"type": "way", "id": 384337679, "nodes": [3876392077, 1319179807, 84693633], "tags": {"cycleway:left": "lane", "cycleway:left:lane": "exclusive", "cycleway:right": "lane", "cycleway:right:lane": "advisory", "highway": "tertiary", "lanes": "3", "lanes:backward": "1", "lanes:forward": "2", "lcn": "yes", "name": "Szent Imre t\u00e9r", "smoothness": "excellent", "surface": "asphalt", "turn:lanes:backward": "through", "turn:lanes:forward": "through|right"}}, {"type": "way", "id": 410498327, "nodes": [244929128, 527360262, 2235427917], "tags": {"highway": "residential", "lcn": "proposed", "name": "Katona J\u00f3zsef utca", "oneway": "no", "surface": "asphalt"}}, {"type": "way", "id": 464981451, "nodes": [244929129, 2235427914, 546925908], "tags": {"highway": "tertiary", "lanes": "2", "lcn": "proposed", "name": "T\u00e1ncsics Mih\u00e1ly utca", "surface": "asphalt"}}, {"type": "way", "id": 464981452, "nodes": [546925908, 2207117179, 2207117166, 2319944142], "tags": {"highway": "tertiary", "lanes": "2", "name": "T\u00e1ncsics Mih\u00e1ly utca", "surface": "asphalt"}}, {"type": "way", "id": 475292403, "nodes": [4690567169, 4690567170], "tags": {"highway": "residential", "name": "D\u00e9li k\u00f6z"}}, {"type": "way", "id": 525853279, "nodes": [1319852150, 2281481719, 1413107975, 4690567170], "tags": {"highway": "tertiary", "name": "D\u00e9li utca"}}, {"type": "way", "id": 528946603, "nodes": [546925910, 2235427919, 244929129], "tags": {"highway": "tertiary", "lanes": "2", "lcn": "proposed", "name": "T\u00e1ncsics Mih\u00e1ly utca", "surface": "asphalt"}}, {"type": "way", "id": 528947242, "nodes": [2281481745, 1020421741], "tags": {"highway": "residential", "lanes": "3", "lanes:backward": "2", "lanes:forward": "1", "lcn": "proposed", "name": "Kar\u00e1csony S\u00e1ndor utca", "turn:lanes:backward": "slight_left|through;right", "turn:lanes:forward": "through"}}, {"type": "way", "id": 528960287, "nodes": [1319180110, 7899955084, 546926154], "tags": {"highway": "tertiary", "lanes": "2", "lcn": "proposed", "name": "Vermes Mikl\u00f3s utca", "old_name": "Kolt\u00f3i Anna utca", "oneway": "yes", "source:name": "http://einfoszab.budapest.hu/list/fovarosi-kozgyules-nyilvanos-ulesei;parenttype=2;parentid=6095;type=3;id=79357", "surface": "asphalt"}}, {"type": "way", "id": 528960288, "nodes": [527360240, 2576631908, 527360249, 282197417], "tags": {"highway": "residential", "lcn": "proposed", "lit": "yes", "name": "Bajcsy-Zsilinszky \u00fat", "surface": "asphalt"}}, {"type": "way", "id": 528960289, "nodes": [527360240, 2576631910, 527360261, 2235270158, 84693632], "tags": {"highway": "residential", "lcn": "proposed", "lit": "yes", "name": "K\u00e1roli G\u00e1sp\u00e1r utca", "surface": "asphalt"}}, {"type": "way", "id": 629934286, "nodes": [2244819882, 8517713344, 514817227], "tags": {"highway": "residential", "lanes": "3", "lanes:backward": "2", "lanes:forward": "1", "lcn": "proposed", "lit": "yes", "name": "Vermes Mikl\u00f3s utca", "old_name": "Kolt\u00f3i Anna utca", "source:name": "http://einfoszab.budapest.hu/list/fovarosi-kozgyules-nyilvanos-ulesei;parenttype=2;parentid=6095;type=3;id=79357", "surface": "asphalt", "turn:lanes:backward": "slight_left|slight_right"}}, {"type": "way", "id": 629934287, "nodes": [2244819769, 2145731910], "tags": {"highway": "tertiary", "name": "K\u00e1roli G\u00e1sp\u00e1r utca"}}, {"type": "way", "id": 636606710, "nodes": [6003111908, 546926234], "tags": {"highway": "residential", "surface": "unpaved"}}, {"type": "way", "id": 646577402, "nodes": [546925901, 1319852156, 1039510283, 1039510284, 1318819100, 2113685774, 244926007], "tags": {"highway": "tertiary", "lane_markings": "no", "lcn": "proposed", "name": "II. R\u00e1k\u00f3czi Ferenc \u00fat", "oneway": "yes", "surface": "asphalt"}}, {"type": "way", "id": 661214952, "nodes": [2129804865, 2281481745], "tags": {"highway": "residential", "lanes": "3", "lanes:backward": "2", "lanes:forward": "1", "name": "Kar\u00e1csony S\u00e1ndor utca", "turn:lanes:backward": "slight_left|through;right", "turn:lanes:forward": "through"}}, {"type": "way", "id": 661214953, "nodes": [1020421741, 6190400270], "tags": {"highway": "residential", "lanes": "3", "lanes:backward": "2", "lanes:forward": "1", "lcn": "proposed", "name": "Kar\u00e1csony S\u00e1ndor utca", "turn:lanes:backward": "slight_left|through;right", "turn:lanes:forward": "through"}}, {"type": "way", "id": 661234469, "nodes": [6190578042, 546925971], "tags": {"cycleway:right": "no", "highway": "tertiary", "lanes": "2", "name": "II. R\u00e1k\u00f3czi Ferenc \u00fat", "oneway": "yes", "surface": "asphalt", "turn:lanes": "through|right"}}, {"type": "way", "id": 661234470, "nodes": [546925898, 1020423332, 84691002, 6190578042], "tags": {"highway": "tertiary", "lane_markings": "no", "name": "II. R\u00e1k\u00f3czi Ferenc \u00fat", "oneway": "yes", "surface": "asphalt"}}, {"type": "way", "id": 661261575, "nodes": [84687274, 1319180120, 6190798620], "tags": {"cycleway:left": "lane", "cycleway:left:lane": "advisory", "highway": "tertiary", "lanes": "3", "lanes:backward": "2", "lanes:forward": "1", "lcn": "yes", "name": "Kossuth Lajos utca", "surface": "asphalt", "turn:lanes:backward": "left|through", "turn:lanes:forward": "through"}}, {"type": "way", "id": 661261579, "nodes": [6190798621, 2113696917, 1319180112, 84687274], "tags": {"highway": "tertiary", "lanes": "3", "lcn": "proposed", "name": "Szent Imre t\u00e9r", "old_name": "Kolt\u00f3i Anna utca", "oneway": "yes", "source:name": "http://einfoszab.budapest.hu/list/fovarosi-kozgyules-nyilvanos-ulesei;parenttype=2;parentid=6095;type=3;id=79357", "surface": "asphalt", "turn:lanes": "left|through|right"}}, {"type": "way", "id": 661261582, "nodes": [6190798622, 3876392078], "tags": {"cycleway:left": "track", "cycleway:right": "lane", "cycleway:right:lane": "advisory", "highway": "tertiary", "lanes": "2", "lanes:backward": "1", "lanes:forward": "1", "lcn": "yes", "name": "Szent Imre t\u00e9r", "smoothness": "excellent", "surface": "asphalt", "turn:lanes:backward": "through;right", "turn:lanes:forward": "through"}}, {"type": "way", "id": 745219293, "nodes": [282197548, 1704207787, 2235270185, 282196265], "tags": {"highway": "residential", "lit": "yes", "name": "\u00c1rp\u00e1d utca", "surface": "asphalt"}}, {"type": "way", "id": 770732455, "nodes": [2281481703, 546925975, 8517725331, 546925964, 8517725330, 6003108882, 546926234, 546925972, 546925962], "tags": {"highway": "residential", "lcn": "proposed", "lit": "yes", "maxweight:hgv": "12", "name": "Pet\u0151fi utca", "sidewalk": "right", "surface": "asphalt"}}, {"type": "way", "id": 770732456, "nodes": [546925964, 1877488588], "tags": {"cycleway:right": "no", "highway": "secondary", "lanes": "2", "name": "Bet\u0171 utca", "oneway": "yes", "surface": "asphalt"}}, {"type": "way", "id": 868044244, "nodes": [84693635, 4690692197, 1877785773], "tags": {"highway": "tertiary", "maxspeed": "30", "motor_vehicle": "destination", "name": "Sz\u00ednesf\u00e9m utca"}}, {"type": "way", "id": 868044246, "nodes": [4690567170, 8091097977], "tags": {"highway": "tertiary", "name": "D\u00e9li utca"}}, {"type": "way", "id": 868044247, "nodes": [1319852151, 2324415268], "tags": {"highway": "tertiary", "maxspeed": "20", "motor_vehicle": "destination", "name": "D\u00e9li utca"}}, {"type": "way", "id": 868044248, "nodes": [8091097977, 1319852151], "tags": {"highway": "tertiary", "motor_vehicle": "destination", "name": "D\u00e9li utca"}}, {"type": "way", "id": 910485010, "nodes": [1319852153, 2163574207, 546925901], "tags": {"highway": "tertiary", "maxspeed": "30", "name": "II. R\u00e1k\u00f3czi Ferenc \u00fat", "oneway": "yes", "source:maxspeed": "sign"}}, {"type": "way", "id": 918310919, "nodes": [282197417, 3066608649, 322687673], "tags": {"highway": "residential", "name": "V\u00e1g\u00f3h\u00edd utca", "surface": "asphalt"}}, {"type": "way", "id": 918310920, "nodes": [282197417, 244929128], "tags": {"highway": "residential", "lcn": "proposed", "lit": "yes", "name": "Bajcsy-Zsilinszky \u00fat", "surface": "asphalt"}}]}